registerfile.v
module registerfile(
    input clk,
    input wr_en,
    input [4:0] wr_index,
    input [31:0] wr_data,
    input [4:0] rd_index1,
    input [4:0] rd_index2,
    output [31:0] rd_data1,
    output [31:0] rd_data2
);

    // Memoria de 32 posiciones de 32 bits
    reg [31:0] mem [0:31];

    // Lógica de lectura combinacional (dual-port)
    // El registro x0 (dirección 0) siempre se lee cero
    assign rd_data1 = (rd_index1 == 5'b00000) ? 32'd0 : mem[rd_index1];
    assign rd_data2 = (rd_index2 == 5'b00000) ? 32'd0 : mem[rd_index2];

    // Lógica de escritura secuencial / sincrónica
    always @(posedge clk) begin
        // Si la escritura está habilitada y no se intenta escribir en x0
        if (wr_en && (wr_index != 5'b00000)) begin
            mem[wr_index] <= wr_data;
        end
    end

endmodule

registerfile_tb.v
`timescale 1ns/1ps

module registerfile_tb;

    // Señales de prueba
    reg clk;
    reg wr_en;
    reg [4:0] wr_index;
    reg [31:0] wr_data;
    reg [4:0] rd_index1;
    reg [4:0] rd_index2;
    
    wire [31:0] rd_data1;
    wire [31:0] rd_data2;

    integer i; // Variable para los bucles for

    // Instanciación del módulo (DUT)
    registerfile uut (
        .clk(clk),
        .wr_en(wr_en),
        .wr_index(wr_index),
        .wr_data(wr_data),
        .rd_index1(rd_index1),
        .rd_index2(rd_index2),
        .rd_data1(rd_data1),
        .rd_data2(rd_data2)
    );

    // Bloque inicial: aplica estímulos
    initial begin
        // Configurar la generación de archivos de volcado para Icarus Verilog y GTKWave
        $dumpfile("registerfile_tb.vcd");
        $dumpvars(0, registerfile_tb);
        
        // Volcar las variables internas de la memoria para verlas gráficamente
        for(i = 0; i < 32; i = i + 1) $dumpvars(0, uut.mem[i]);

        // Muestra en consola los valores de interés cada vez que cambien usando $monitor[cite: 1]
        $monitor("Tiempo=%0t | clk=%b | wr_en=%b | wr_index=%d | wr_data=%h || rd_index1=%d -> rd_data1=%h | rd_index2=%d -> rd_data2=%h", 
                 $time, clk, wr_en, wr_index, wr_data, rd_index1, rd_data1, rd_index2, rd_data2);

        // 1. Inicialización de señales
        clk = 0;
        wr_en = 0;
        wr_index = 0;
        wr_data = 0;
        rd_index1 = 0;
        rd_index2 = 0;

        // 2. Prueba de escritura en el registro x5
        #10;
        wr_en = 1;
        wr_index = 5;
        wr_data = 32'hAAAA_BBBB;
        
        // 3. Prueba de escritura en el registro x10
        #10;
        wr_index = 10;
        wr_data = 32'h1111_2222;

        // 4. Prueba de escritura en x0 (No debería modificarse, x0 siempre es cero)[cite: 1]
        #10;
        wr_index = 0;
        wr_data = 32'hFFFF_FFFF;

        // 5. Prueba de lectura dual (Desactivando escritura)
        #10;
        wr_en = 0;
        rd_index1 = 5;   // Debería leer AAAA_BBBB
        rd_index2 = 10;  // Debería leer 1111_2222

        // 6. Prueba de lectura del registro x0
        #10;
        rd_index1 = 0;   // Debería leer 0000_0000

        // Fin de la simulación
        #20;
        $finish; 
    end

    // Generación de la señal de reloj
    always begin
        #5 clk = ~clk;
    end

endmodule

registerfile_tb.vcd
$date
	Wed Sep  9 09:43:41 2026
$end
$version
	Icarus Verilog
$end
$timescale
	1ps
$end
$scope module registerfile_tb $end
$var wire 32 ! rd_data2 [31:0] $end
$var wire 32 " rd_data1 [31:0] $end
$var reg 1 # clk $end
$var reg 5 $ rd_index1 [4:0] $end
$var reg 5 % rd_index2 [4:0] $end
$var reg 32 & wr_data [31:0] $end
$var reg 1 ' wr_en $end
$var reg 5 ( wr_index [4:0] $end
$var integer 32 ) i [31:0] $end
$scope module uut $end
$var wire 1 # clk $end
$var wire 5 * rd_index1 [4:0] $end
$var wire 5 + rd_index2 [4:0] $end
$var wire 32 , wr_data [31:0] $end
$var wire 1 ' wr_en $end
$var wire 5 - wr_index [4:0] $end
$var wire 32 . rd_data2 [31:0] $end
$var wire 32 / rd_data1 [31:0] $end
$upscope $end
$upscope $end
$scope module registerfile_tb $end
$scope module uut $end
$var reg 32 0 \mem[0] [31:0] $end
$upscope $end
$upscope $end
$scope module registerfile_tb $end
$scope module uut $end
$var reg 32 1 \mem[1] [31:0] $end
$upscope $end
$upscope $end
$scope module registerfile_tb $end
$scope module uut $end
$var reg 32 2 \mem[2] [31:0] $end
$upscope $end
$upscope $end
$scope module registerfile_tb $end
$scope module uut $end
$var reg 32 3 \mem[3] [31:0] $end
$upscope $end
$upscope $end
$scope module registerfile_tb $end
$scope module uut $end
$var reg 32 4 \mem[4] [31:0] $end
$upscope $end
$upscope $end
$scope module registerfile_tb $end
$scope module uut $end
$var reg 32 5 \mem[5] [31:0] $end
$upscope $end
$upscope $end
$scope module registerfile_tb $end
$scope module uut $end
$var reg 32 6 \mem[6] [31:0] $end
$upscope $end
$upscope $end
$scope module registerfile_tb $end
$scope module uut $end
$var reg 32 7 \mem[7] [31:0] $end
$upscope $end
$upscope $end
$scope module registerfile_tb $end
$scope module uut $end
$var reg 32 8 \mem[8] [31:0] $end
$upscope $end
$upscope $end
$scope module registerfile_tb $end
$scope module uut $end
$var reg 32 9 \mem[9] [31:0] $end
$upscope $end
$upscope $end
$scope module registerfile_tb $end
$scope module uut $end
$var reg 32 : \mem[10] [31:0] $end
$upscope $end
$upscope $end
$scope module registerfile_tb $end
$scope module uut $end
$var reg 32 ; \mem[11] [31:0] $end
$upscope $end
$upscope $end
$scope module registerfile_tb $end
$scope module uut $end
$var reg 32 < \mem[12] [31:0] $end
$upscope $end
$upscope $end
$scope module registerfile_tb $end
$scope module uut $end
$var reg 32 = \mem[13] [31:0] $end
$upscope $end
$upscope $end
$scope module registerfile_tb $end
$scope module uut $end
$var reg 32 > \mem[14] [31:0] $end
$upscope $end
$upscope $end
$scope module registerfile_tb $end
$scope module uut $end
$var reg 32 ? \mem[15] [31:0] $end
$upscope $end
$upscope $end
$scope module registerfile_tb $end
$scope module uut $end
$var reg 32 @ \mem[16] [31:0] $end
$upscope $end
$upscope $end
$scope module registerfile_tb $end
$scope module uut $end
$var reg 32 A \mem[17] [31:0] $end
$upscope $end
$upscope $end
$scope module registerfile_tb $end
$scope module uut $end
$var reg 32 B \mem[18] [31:0] $end
$upscope $end
$upscope $end
$scope module registerfile_tb $end
$scope module uut $end
$var reg 32 C \mem[19] [31:0] $end
$upscope $end
$upscope $end
$scope module registerfile_tb $end
$scope module uut $end
$var reg 32 D \mem[20] [31:0] $end
$upscope $end
$upscope $end
$scope module registerfile_tb $end
$scope module uut $end
$var reg 32 E \mem[21] [31:0] $end
$upscope $end
$upscope $end
$scope module registerfile_tb $end
$scope module uut $end
$var reg 32 F \mem[22] [31:0] $end
$upscope $end
$upscope $end
$scope module registerfile_tb $end
$scope module uut $end
$var reg 32 G \mem[23] [31:0] $end
$upscope $end
$upscope $end
$scope module registerfile_tb $end
$scope module uut $end
$var reg 32 H \mem[24] [31:0] $end
$upscope $end
$upscope $end
$scope module registerfile_tb $end
$scope module uut $end
$var reg 32 I \mem[25] [31:0] $end
$upscope $end
$upscope $end
$scope module registerfile_tb $end
$scope module uut $end
$var reg 32 J \mem[26] [31:0] $end
$upscope $end
$upscope $end
$scope module registerfile_tb $end
$scope module uut $end
$var reg 32 K \mem[27] [31:0] $end
$upscope $end
$upscope $end
$scope module registerfile_tb $end
$scope module uut $end
$var reg 32 L \mem[28] [31:0] $end
$upscope $end
$upscope $end
$scope module registerfile_tb $end
$scope module uut $end
$var reg 32 M \mem[29] [31:0] $end
$upscope $end
$upscope $end
$scope module registerfile_tb $end
$scope module uut $end
$var reg 32 N \mem[30] [31:0] $end
$upscope $end
$upscope $end
$scope module registerfile_tb $end
$scope module uut $end
$var reg 32 O \mem[31] [31:0] $end
$upscope $end
$upscope $end
$enddefinitions $end
$comment Show the parameter values. $end
$dumpall
$end
#0
$dumpvars
bx O
bx N
bx M
bx L
bx K
bx J
bx I
bx H
bx G
bx F
bx E
bx D
bx C
bx B
bx A
bx @
bx ?
bx >
bx =
bx <
bx ;
bx :
bx 9
bx 8
bx 7
bx 6
bx 5
bx 4
bx 3
bx 2
bx 1
bx 0
b0 /
b0 .
b0 -
b0 ,
b0 +
b0 *
b100000 )
b0 (
0'
b0 &
b0 %
b0 $
0#
b0 "
b0 !
$end
#5000
1#
#10000
0#
b10101010101010101011101110111011 &
b10101010101010101011101110111011 ,
b101 (
b101 -
1'
#15000
b10101010101010101011101110111011 5
1#
#20000
0#
b10001000100010010001000100010 &
b10001000100010010001000100010 ,
b1010 (
b1010 -
#25000
b10001000100010010001000100010 :
1#
#30000
0#
b11111111111111111111111111111111 &
b11111111111111111111111111111111 ,
b0 (
b0 -
#35000
1#
#40000
b10001000100010010001000100010 !
b10001000100010010001000100010 .
b10101010101010101011101110111011 "
b10101010101010101011101110111011 /
0#
b1010 %
b1010 +
b101 $
b101 *
0'
#45000
1#
#50000
b0 "
b0 /
0#
b0 $
b0 *
