alu.v
module alu (
    input [31:0] A,
    input [31:0] B,
    input [2:0] op,
    output [31:0] ALU_out
);

    assign ALU_out = 
        (op == 3'b000) ? A + B :  // Suma (add)
        (op == 3'b001) ? A - B :  // Resta (sub)
        (op == 3'b010) ? A & B :  // AND (and)
        (op == 3'b011) ? A | B :  // OR (or)
        (op == 3'b100) ? A ^ B :  // XOR (xor)
                         32'd0;

endmodule

registerfile.v
module registerfile(
    input clk,
    input wr_en,
    input [4:0] wr_index,
    input [31:0] wr_data,
    input [4:0] rd_index1,
    input [4:0] rd_index2,
    output [31:0] rd_data1,
    output [31:0] rd_data2
);

    // Memoria de 32 posiciones de 32 bits
    reg [31:0] mem [0:31];

    // Lógica de lectura combinacional (dual-port)
    // El registro x0 (dirección 0) siempre se lee cero
    assign rd_data1 = (rd_index1 == 5'b00000) ? 32'd0 : mem[rd_index1];
    assign rd_data2 = (rd_index2 == 5'b00000) ? 32'd0 : mem[rd_index2];

    // Lógica de escritura secuencial / sincrónica
    always @(posedge clk) begin
        // Si la escritura está habilitada y no se intenta escribir en x0
        if (wr_en && (wr_index != 5'b00000)) begin
            mem[wr_index] <= wr_data;
        end
    end

endmodule

riscv.v
module riscv (
    input clk,          // Reloj del procesador
    input rst,          // Reset del procesador
    input [31:0] instr  // Instrucción de entrada
);

    reg [31:0] IR; // Registro de instrucción
    always @(posedge clk) begin
        IR <= instr;
    end

    // Señales del registro de instrucción

    wire [6:0] funct7;
    wire [4:0] rs2;
    wire [4:0] rs1;
    wire [2:0] funct3;
    wire [4:0] rd;
    wire [6:0] opcode;

    // Campos de registro 

    assign funct7 = IR[31:25];
    assign rs2    = IR[24:20];
    assign rs1    = IR[19:15];
    assign funct3 = IR[14:12];
    assign rd     = IR[11:7];
    assign opcode = IR[6:0];

    // tipos de instruccion
    wire is_valid;
    wire is_r_instr;
    wire is_i_instr;
    wire is_s_instr;
    wire is_b_instr;
    wire is_u_instr;
    wire is_j_instr;

    // Verificación 

    assign is_valid   = (opcode[1:0] == 2'b11); 
    
    // Identificación del tipo

    assign is_r_instr = (opcode[6:2] == 5'b01100);
    assign is_i_instr = (opcode[6:2] == 5'b00000) | (opcode[6:2] == 5'b00100) | (opcode[6:2] == 5'b11001);
    assign is_s_instr = (opcode[6:2] == 5'b01000);
    assign is_b_instr = (opcode[6:2] == 5'b11000);
    assign is_u_instr = (opcode[6:2] == 5'b00101) | (opcode[6:2] == 5'b01101);
    assign is_j_instr = (opcode[6:2] == 5'b11011);

    // EXTRACCIÓN DEL VALOR INMEDIATO Y VALIDEZ
  
    wire [31:0] imm;
    wire imm_valid;

    // Valor

    assign imm[31:0] = 
        is_i_instr ? { {21{IR[31]}}, IR[30:20] } :
        is_s_instr ? { {21{IR[31]}}, IR[30:25], IR[11:7] } :
        is_b_instr ? { {20{IR[31]}}, IR[7], IR[30:25], IR[11:8], 1'b0 } :
        is_u_instr ? { IR[31:12], 12'b0 } :
        is_j_instr ? { {12{IR[31]}}, IR[19:12], IR[20], IR[30:21], 1'b0 } :
        32'b0;

    // El campo valido

    assign imm_valid = is_i_instr | is_s_instr | is_b_instr | is_u_instr | is_j_instr;


    // Salidas del register file
    wire [31:0] src1_value;
    wire [31:0] src2_value;

    // Operandos de entrada a la ALU
    wire [31:0] alu_a;
    wire [31:0] alu_b;

    // Salida de la ALU
    wire [31:0] alu_out;

    // Señales de control de la Unidad de Control (CU)
    wire wr_en;
    wire [10:0] dec_bits;
    wire [9:0]  dec_bits2;
    wire is_add, is_sub, is_and, is_or, is_xor;
    wire is_addi, is_xori, is_ori, is_andi;

    // CABLEADO 
    assign alu_a = src1_value; 
    
    // Reutilización de la ALU

    assign alu_b = imm_valid ? imm[31:0] : src2_value;

    // CONTROL UNIT (CU) - DECODIFICACIÓN DE OPERACIONES
    // Decodificador 

    assign dec_bits = {funct7[5], funct3, opcode};
    
    // Decodificador para instrucciones tipo I 
    assign dec_bits2 = {funct3, opcode};

    // Identificación de instrucciones tipo R 

    assign is_add = (dec_bits == 11'b0_000_0110011);
    assign is_sub = (dec_bits == 11'b1_000_0110011);
    assign is_xor = (dec_bits == 11'b0_100_0110011);
    assign is_or  = (dec_bits == 11'b0_110_0110011);
    assign is_and = (dec_bits == 11'b0_111_0110011);

    // Identificación de instrucciones tipo I 

    assign is_addi = (dec_bits2 == 10'b000_0010011);
    assign is_xori = (dec_bits2 == 10'b100_0010011);
    assign is_ori  = (dec_bits2 == 10'b110_0010011);
    assign is_andi = (dec_bits2 == 10'b111_0010011);

    // Habilitador de escritura 

    assign wr_en = (is_r_instr | is_i_instr | is_u_instr | is_j_instr) & is_valid;

    // Código de operación enviado a la ALU combinando ambas variantes (R e I)

    wire [2:0] alu_op;
    assign alu_op = (is_add | is_addi) ? 3'b000 :
                    (is_sub)           ? 3'b001 :
                    (is_and | is_andi) ? 3'b010 :
                    (is_or  | is_ori)  ? 3'b011 :
                    (is_xor | is_xori) ? 3'b100 : 3'b000;

    registerfile rv_rf (
        .clk(clk),
        .wr_en(wr_en),
        .wr_index(rd),
        .wr_data(alu_out),
        .rd_index1(rs1),
        .rd_data1(src1_value),
        .rd_index2(rs2),
        .rd_data2(src2_value)
    );

    // Instanciación de la ALU[cite: 6]
    alu rv_alu (
        .A(alu_a),
        .B(alu_b),
        .ALU_out(alu_out),
        .op(alu_op)
    );

endmodule

riscv_tb.v
`timescale 1ns/1ps

module riscv_tb;

    // 1. Señales de prueba
    reg clk;
    reg rst;
    reg [31:0] instr;
    
    integer i; // Variable para iterar en el volcado de memoria

    // 2. Instanciación del módulo RISC-V (DUT)
    riscv uut (
        .clk(clk),
        .rst(rst),
        .instr(instr)
    );

    // 3. Generación de la señal de reloj (Período de 10ns)
    always begin
        #5 clk = ~clk;
    end

    // 4. Bloque inicial: configuración y estímulos
    initial begin
        // Configurar la generación de archivos de volcado para Icarus Verilog y GTKWave[cite: 4]
        $dumpfile("riscv_tb.vcd");
        $dumpvars(0, riscv_tb);
        
        // Volcar las variables internas de la memoria del Register File para verlas gráficamente[cite: 4]
        for(i = 0; i < 32; i = i + 1) $dumpvars(0, uut.rv_rf.mem[i]);

        // Muestra en consola los valores de interés cada vez que cambien usando $monitor[cite: 2]
        // Se monitorea la instrucción, el registro destino (rd), la salida de la ALU y la señal de escritura
        $monitor("Tiempo=%0t | clk=%b | instr=%h | rd=%d | alu_out=%d | wr_en=%b", 
                 $time, clk, instr, uut.rd, uut.alu_out, uut.wr_en);

        // Inicialización de señales
        clk = 0;
        rst = 1;
        instr = 32'd0;

        #10;
        rst = 0; // Desactivar reset

        /* PRUEBA DE INSTRUCCIONES TIPO I y TIPO R */
        
        // Estímulo 1: addi x5, x0, 10 (Instrucción Tipo I)
        // imm=10, rs1=0, funct3=000, rd=5, opcode=0010011 -> 32'h00A00293
        #10;
        instr = 32'h00A00293; 

        // Estímulo 2: addi x6, x5, 20 (Instrucción Tipo I)
        // imm=20, rs1=5, funct3=000, rd=6, opcode=0010011 -> 32'h01428313
        #10;
        instr = 32'h01428313;

        // Estímulo 3: add x7, x5, x6 (Instrucción Tipo R)
        // Suma los registros x5 y x6, y guarda en x7 (10 + 20 = 30)
        // funct7=0000000, rs2=6, rs1=5, funct3=000, rd=7, opcode=0110011 -> 32'h006283B3
        #10;
        instr = 32'h006283B3;

        // Estímulo 4: ori x8, x5, 5 (Instrucción Tipo I con operaciones lógicas)
        // Hace un OR entre x5 (valor 10 = 1010) y 5 (0101). Resultado = 15. Guarda en x8
        // imm=5, rs1=5, funct3=110, rd=8, opcode=0010011 -> 32'h0052E413
        #10;
        instr = 32'h0052E413;

        // Estímulo 5: sub x9, x6, x5 (Instrucción Tipo R)
        // Resta x5 de x6, guarda en x9 (20 - 10 = 10)
        // funct7=0100000, rs2=5, rs1=6, funct3=000, rd=9, opcode=0110011 -> 32'h405304B3
        #10;
        instr = 32'h405304B3;

        // Esperar un ciclo adicional para que se registre la última instrucción
        #20;
        $finish; // Fin de la simulación[cite: 2]
    end

endmodule

riscv_tb.vcd
$date
	Tue Sep 22 00:42:45 2026
$end
$version
	Icarus Verilog
$end
$timescale
	1ps
$end
$scope module riscv_tb $end
$var reg 1 ! clk $end
$var reg 32 " instr [31:0] $end
$var reg 1 # rst $end
$var integer 32 $ i [31:0] $end
$scope module uut $end
$var wire 32 % alu_a [31:0] $end
$var wire 1 ! clk $end
$var wire 1 & imm_valid $end
$var wire 32 ' instr [31:0] $end
$var wire 1 ( is_i_instr $end
$var wire 1 ) is_u_instr $end
$var wire 1 # rst $end
$var wire 1 * wr_en $end
$var wire 32 + src2_value [31:0] $end
$var wire 32 , src1_value [31:0] $end
$var wire 5 - rs2 [4:0] $end
$var wire 5 . rs1 [4:0] $end
$var wire 5 / rd [4:0] $end
$var wire 7 0 opcode [6:0] $end
$var wire 1 1 is_xori $end
$var wire 1 2 is_xor $end
$var wire 1 3 is_valid $end
$var wire 1 4 is_sub $end
$var wire 1 5 is_s_instr $end
$var wire 1 6 is_r_instr $end
$var wire 1 7 is_ori $end
$var wire 1 8 is_or $end
$var wire 1 9 is_j_instr $end
$var wire 1 : is_b_instr $end
$var wire 1 ; is_andi $end
$var wire 1 < is_and $end
$var wire 1 = is_addi $end
$var wire 1 > is_add $end
$var wire 32 ? imm [31:0] $end
$var wire 7 @ funct7 [6:0] $end
$var wire 3 A funct3 [2:0] $end
$var wire 10 B dec_bits2 [9:0] $end
$var wire 11 C dec_bits [10:0] $end
$var wire 32 D alu_out [31:0] $end
$var wire 3 E alu_op [2:0] $end
$var wire 32 F alu_b [31:0] $end
$var reg 32 G IR [31:0] $end
$scope module rv_alu $end
$var wire 32 H A [31:0] $end
$var wire 32 I B [31:0] $end
$var wire 3 J op [2:0] $end
$var wire 32 K ALU_out [31:0] $end
$upscope $end
$scope module rv_rf $end
$var wire 1 ! clk $end
$var wire 5 L rd_index1 [4:0] $end
$var wire 5 M rd_index2 [4:0] $end
$var wire 32 N wr_data [31:0] $end
$var wire 1 * wr_en $end
$var wire 5 O wr_index [4:0] $end
$var wire 32 P rd_data2 [31:0] $end
$var wire 32 Q rd_data1 [31:0] $end
$upscope $end
$upscope $end
$upscope $end
$scope module riscv_tb $end
$scope module uut $end
$scope module rv_rf $end
$var reg 32 R \mem[0] [31:0] $end
$upscope $end
$upscope $end
$upscope $end
$scope module riscv_tb $end
$scope module uut $end
$scope module rv_rf $end
$var reg 32 S \mem[1] [31:0] $end
$upscope $end
$upscope $end
$upscope $end
$scope module riscv_tb $end
$scope module uut $end
$scope module rv_rf $end
$var reg 32 T \mem[2] [31:0] $end
$upscope $end
$upscope $end
$upscope $end
$scope module riscv_tb $end
$scope module uut $end
$scope module rv_rf $end
$var reg 32 U \mem[3] [31:0] $end
$upscope $end
$upscope $end
$upscope $end
$scope module riscv_tb $end
$scope module uut $end
$scope module rv_rf $end
$var reg 32 V \mem[4] [31:0] $end
$upscope $end
$upscope $end
$upscope $end
$scope module riscv_tb $end
$scope module uut $end
$scope module rv_rf $end
$var reg 32 W \mem[5] [31:0] $end
$upscope $end
$upscope $end
$upscope $end
$scope module riscv_tb $end
$scope module uut $end
$scope module rv_rf $end
$var reg 32 X \mem[6] [31:0] $end
$upscope $end
$upscope $end
$upscope $end
$scope module riscv_tb $end
$scope module uut $end
$scope module rv_rf $end
$var reg 32 Y \mem[7] [31:0] $end
$upscope $end
$upscope $end
$upscope $end
$scope module riscv_tb $end
$scope module uut $end
$scope module rv_rf $end
$var reg 32 Z \mem[8] [31:0] $end
$upscope $end
$upscope $end
$upscope $end
$scope module riscv_tb $end
$scope module uut $end
$scope module rv_rf $end
$var reg 32 [ \mem[9] [31:0] $end
$upscope $end
$upscope $end
$upscope $end
$scope module riscv_tb $end
$scope module uut $end
$scope module rv_rf $end
$var reg 32 \ \mem[10] [31:0] $end
$upscope $end
$upscope $end
$upscope $end
$scope module riscv_tb $end
$scope module uut $end
$scope module rv_rf $end
$var reg 32 ] \mem[11] [31:0] $end
$upscope $end
$upscope $end
$upscope $end
$scope module riscv_tb $end
$scope module uut $end
$scope module rv_rf $end
$var reg 32 ^ \mem[12] [31:0] $end
$upscope $end
$upscope $end
$upscope $end
$scope module riscv_tb $end
$scope module uut $end
$scope module rv_rf $end
$var reg 32 _ \mem[13] [31:0] $end
$upscope $end
$upscope $end
$upscope $end
$scope module riscv_tb $end
$scope module uut $end
$scope module rv_rf $end
$var reg 32 ` \mem[14] [31:0] $end
$upscope $end
$upscope $end
$upscope $end
$scope module riscv_tb $end
$scope module uut $end
$scope module rv_rf $end
$var reg 32 a \mem[15] [31:0] $end
$upscope $end
$upscope $end
$upscope $end
$scope module riscv_tb $end
$scope module uut $end
$scope module rv_rf $end
$var reg 32 b \mem[16] [31:0] $end
$upscope $end
$upscope $end
$upscope $end
$scope module riscv_tb $end
$scope module uut $end
$scope module rv_rf $end
$var reg 32 c \mem[17] [31:0] $end
$upscope $end
$upscope $end
$upscope $end
$scope module riscv_tb $end
$scope module uut $end
$scope module rv_rf $end
$var reg 32 d \mem[18] [31:0] $end
$upscope $end
$upscope $end
$upscope $end
$scope module riscv_tb $end
$scope module uut $end
$scope module rv_rf $end
$var reg 32 e \mem[19] [31:0] $end
$upscope $end
$upscope $end
$upscope $end
$scope module riscv_tb $end
$scope module uut $end
$scope module rv_rf $end
$var reg 32 f \mem[20] [31:0] $end
$upscope $end
$upscope $end
$upscope $end
$scope module riscv_tb $end
$scope module uut $end
$scope module rv_rf $end
$var reg 32 g \mem[21] [31:0] $end
$upscope $end
$upscope $end
$upscope $end
$scope module riscv_tb $end
$scope module uut $end
$scope module rv_rf $end
$var reg 32 h \mem[22] [31:0] $end
$upscope $end
$upscope $end
$upscope $end
$scope module riscv_tb $end
$scope module uut $end
$scope module rv_rf $end
$var reg 32 i \mem[23] [31:0] $end
$upscope $end
$upscope $end
$upscope $end
$scope module riscv_tb $end
$scope module uut $end
$scope module rv_rf $end
$var reg 32 j \mem[24] [31:0] $end
$upscope $end
$upscope $end
$upscope $end
$scope module riscv_tb $end
$scope module uut $end
$scope module rv_rf $end
$var reg 32 k \mem[25] [31:0] $end
$upscope $end
$upscope $end
$upscope $end
$scope module riscv_tb $end
$scope module uut $end
$scope module rv_rf $end
$var reg 32 l \mem[26] [31:0] $end
$upscope $end
$upscope $end
$upscope $end
$scope module riscv_tb $end
$scope module uut $end
$scope module rv_rf $end
$var reg 32 m \mem[27] [31:0] $end
$upscope $end
$upscope $end
$upscope $end
$scope module riscv_tb $end
$scope module uut $end
$scope module rv_rf $end
$var reg 32 n \mem[28] [31:0] $end
$upscope $end
$upscope $end
$upscope $end
$scope module riscv_tb $end
$scope module uut $end
$scope module rv_rf $end
$var reg 32 o \mem[29] [31:0] $end
$upscope $end
$upscope $end
$upscope $end
$scope module riscv_tb $end
$scope module uut $end
$scope module rv_rf $end
$var reg 32 p \mem[30] [31:0] $end
$upscope $end
$upscope $end
$upscope $end
$scope module riscv_tb $end
$scope module uut $end
$scope module rv_rf $end
$var reg 32 q \mem[31] [31:0] $end
$upscope $end
$upscope $end
$upscope $end
$enddefinitions $end
$comment Show the parameter values. $end
$dumpall
$end
#0
$dumpvars
bx q
bx p
bx o
bx n
bx m
bx l
bx k
bx j
bx i
bx h
bx g
bx f
bx e
bx d
bx c
bx b
bx a
bx `
bx _
bx ^
bx ]
bx \
bx [
bx Z
bx Y
bx X
bx W
bx V
bx U
bx T
bx S
bx R
bx Q
bx P
bx O
bx N
bx M
bx L
bx K
bx J
bx I
bx H
bx G
bx F
bx E
bx D
bx C
bx B
bx A
bx @
bx ?
x>
x=
x<
x;
x:
x9
x8
x7
x6
x5
x4
x3
x2
x1
bx 0
bx /
bx .
bx -
bx ,
bx +
x*
x)
x(
b0 '
x&
bx %
b100000 $
1#
b0 "
0!
$end
#5000
1&
b0 D
b0 K
b0 N
b0 E
b0 J
1(
b0 F
b0 I
0*
0)
b0 ?
b0 +
b0 P
b0 %
b0 H
b0 ,
b0 Q
03
06
05
0:
09
0>
04
02
08
0<
b0 C
0=
01
07
0;
b0 B
b0 @
b0 -
b0 M
b0 .
b0 L
b0 A
b0 /
b0 O
b0 0
b0 G
1!
#10000
0!
0#
#15000
1!
#20000
0!
b101000000000001010010011 "
b101000000000001010010011 '
#25000
b1010 D
b1010 K
b1010 N
b1010 F
b1010 I
1*
b1010 ?
bx +
bx P
13
b10011 C
1=
b10011 B
b1010 -
b1010 M
b101 /
b101 O
b10011 0
b101000000000001010010011 G
1!
#30000
0!
b1010000101000001100010011 "
b1010000101000001100010011 '
#35000
b10100 F
b10100 I
b11110 D
b11110 K
b11110 N
b10100 ?
b1010 %
b1010 H
b1010 ,
b1010 Q
b10100 -
b10100 M
b101 .
b101 L
b110 /
b110 O
b1010000101000001100010011 G
b1010 W
1!
#40000
0!
b11000101000001110110011 "
b11000101000001110110011 '
#45000
0&
b101000 D
b101000 K
b101000 N
0(
b11110 F
b11110 I
b11110 +
b11110 P
b0 ?
16
1>
b110011 C
0=
b110011 B
b110 -
b110 M
b111 /
b111 O
b110011 0
b11110 X
b11000101000001110110011 G
1!
#50000
0!
b10100101110010000010011 "
b10100101110010000010011 '
#55000
1&
b11 E
b11 J
1*
b1111 D
b1111 K
b1111 N
b101 ?
b101 F
b101 I
1(
b1010 +
b1010 P
06
0>
b1100010011 C
17
b1100010011 B
b101 -
b101 M
b110 A
b1000 /
b1000 O
b10011 0
b10100101110010000010011 G
b101000 Y
1!
#60000
0!
b1000000010100110000010010110011 "
b1000000010100110000010010110011 '
#65000
0&
b10100 D
b10100 K
b10100 N
0(
b1 E
b1 J
b1010 F
b1010 I
14
b11110 %
b11110 H
b11110 ,
b11110 Q
b0 ?
16
0>
b10000110011 C
07
b110011 B
b100000 @
b110 .
b110 L
b0 A
b1001 /
b1001 O
b110011 0
b1111 Z
b1000000010100110000010010110011 G
1!
#70000
0!
#75000
b10100 [
1!
