mcu.v
// Declaración de la memoria SRAM de datos (DMEM)
module sram_32x #(
    parameter WORDS = 1024
) (
    input wire clk,
    input wire [9:0] addr,
    input wire wr_en,
    input wire rd_en,
    input wire [31:0] wr_data,
    output wire [31:0] rd_data
);
    reg [31:0] mem [0:WORDS-1];
    reg [31:0] rd_reg;

    always @(posedge clk) begin
        if (wr_en) begin
            mem[addr] <= wr_data;
        end
        if (rd_en) begin
            rd_reg <= mem[addr];
        end
    end

    // Alta impedancia cuando drd_en no está activo para evitar cortocircuitos
    assign rd_data = rd_en ? rd_reg : 32'bz;
endmodule

module mcu (
    input wire clk, // Reloj del microcontrolador
    input wire rst  // Reset del microcontrolador
);
    // Buses con la memoria de programa (IMEM)
    wire [31:0] instr; // Instrucción leída
    wire [31:0] iaddr; // Dirección del PC emitida por la CPU

    // Buses con la memoria de datos (DMEM)
    wire [31:0] daddr;     // Dirección en la DMEM
    wire [31:0] ddata_in;  // Bus de datos DMEM (entrada)
    wire [31:0] ddata_out; // Bus de datos DMEM (salida)
    wire dwr_en;           // Señal de escritura en DMEM
    wire drd_en;           // Señal de lectura en DMEM

    // Instancia de la CPU RISC-V
    riscv cpu (
        .rst(rst),
        .clk(clk),
        .instr(instr),
        .iaddr(iaddr),
        .daddr(daddr),
        .ddata_in(ddata_in),
        .ddata_out(ddata_out),
        .dwr_en(dwr_en),
        .drd_en(drd_en)
    );

    // Instancia de la Memoria ROM de programa (Sincrónica)
    rom4096x32 IMEM (
        .clk(clk),
        .data(instr),
        .addr(iaddr[13:2]) 
    );

    // Instancia de la Memoria RAM de datos (DMEM)
    sram_32x DMEM (
        .clk(clk),
        .addr(daddr[11:2]), // Ignoramos los dos bits menos significativos por alineación de 4 bytes
        .wr_en(dwr_en),
        .rd_en(drd_en),
        .wr_data(ddata_out),
        .rd_data(ddata_in)
    );

endmodule

rom4096x32.v
module rom4096x32 (
    input wire clk,         // Añadida entrada de reloj para hacerla sincrónica
    input wire [11:0] addr, 
    output reg [31:0] data  
);
    // Memoria RAM/ROM de 4096 posiciones de 32 bits
    reg [31:0] mem [0:4095];

    // Inicialización cargando el archivo hex
    initial begin
        // Lee el archivo hexadecimal y lo carga en la memoria
        $readmemh("test_program.hex", mem);
    end

    // Lectura sincrónica (dependiente del reloj)
    always @(posedge clk) begin
        data <= mem[addr];
    end
endmodule

alu.v
module alu (
    input wire [31:0] a,
    input wire [31:0] b,
    input wire [3:0] op, // Ampliado a 4 bits para soportar todas las operaciones
    output reg [31:0] out
);

  
    // PASO 3: Cálculos previos de la ALU

    wire [4:0]  shamt;
    wire [63:0] a_ext;
    wire [31:0] sltu_result;
    wire [31:0] slt_result;

    // Valor del shift
    assign shamt = b[4:0];

    // Extensión de signo de la entrada 'a' para 64 bits (útil para SRA)
    assign a_ext = { {32{a[31]}}, a };

    // Valor obtenido por set if less than unsigned (sltu)
    assign sltu_result = {31'b0, a < b};

    // Valor obtenido por set if less than (signed)
    assign slt_result = (a[31] == b[31]) ? sltu_result : {31'b0, a[31]};
   



    // PASO 4 (Parte 1): Ampliar el MUX de la ALU
  
    always @(*) begin
        case (op)
            4'b0000: out = a + b;           // ADD / ADDI / LUI / AUIPC (Suman)
            4'b1000: out = a - b;           // SUB
            4'b0001: out = a << shamt;      // SLL / SLLI
            4'b0010: out = slt_result;      // SLT / SLTI
            4'b0011: out = sltu_result;     // SLTU / SLTIU
            4'b0100: out = a ^ b;           // XOR / XORI
            4'b0101: out = a >> shamt;      // SRL / SRLI
            4'b1101: out = a_ext >> shamt;  // SRA / SRAI (Aritmético usa a_ext)
            4'b0110: out = a | b;           // OR / ORI
            4'b0111: out = a & b;           // AND / ANDI
            default: out = 32'd0;
        endcase
    end
    
endmodule

registerfile.v
module registerfile (
    input wire clk,
    input wire we,
    input wire [4:0] waddr,
    input wire [4:0] raddr1,
    input wire [4:0] raddr2,
    input wire [31:0] wdata,
    output wire [31:0] rdata1,
    output wire [31:0] rdata2
);
    reg [31:0] mem [0:31];

    // Inicialización a 0 de todos los registros para evitar x (rojo) en la simulación
    integer k;
    initial begin
        for (k = 0; k < 32; k = k + 1) begin
            mem[k] = 32'd0;
        end
    end

    // Escritura sincrónica (el registro x0 siempre se mantiene en 0)
    always @(posedge clk) begin
        if (we && (waddr != 5'd0)) begin
            mem[waddr] <= wdata;
        end
    end

    // Lectura combinacional
    assign rdata1 = (raddr1 == 5'd0) ? 32'd0 : mem[raddr1];
    assign rdata2 = (raddr2 == 5'd0) ? 32'd0 : mem[raddr2];

endmodule

riscv.v
module riscv (
    input wire clk,
    input wire rst,
    input wire [31:0] instr,
    output wire [31:0] iaddr,
    output wire [31:0] daddr,
    input wire [31:0] ddata_in,
    output wire [31:0] ddata_out,
    output wire dwr_en,
    output wire drd_en
);


    // 1. Contador de Programa (PC) y Control de Estados (4 ciclos de reloj)
  
    reg [31:0] pc;
    assign iaddr = pc;

    // Contador en anillo para la máquina de estados de 4 pasos (Fetch, Decode, Execute, Execute2)
    reg state_fetch, state_decode, state_execute, state_execute2;

    always @(negedge clk) begin
        if (rst) begin
            state_fetch    <= 1'b1;
            state_decode   <= 1'b0;
            state_execute  <= 1'b0;
            state_execute2 <= 1'b0;

        end else begin
            state_fetch    <= state_execute2;
            state_decode   <= state_fetch;
            state_execute  <= state_decode;
            state_execute2 <= state_execute;
        end
    end

    // Registro de Instrucción (IR)
    reg [31:0] IR;
    always @(posedge clk) begin
        if (rst) IR <= 32'd0;
        else if (state_fetch) IR <= instr;
    end

    // ------------------------------------------------------------------------
    // 2. Decodificación de Campos e Instrucciones (Requeridas por la Guía)
    // ------------------------------------------------------------------------
    wire [6:0] opcode = IR[6:0];
    wire [4:0] rd     = IR[11:7];
    wire [2:0] funct3 = IR[14:12];
    wire [4:0] rs1    = IR[19:15];
    wire [4:0] rs2    = IR[24:20];
    wire [6:0] funct7 = IR[31:25];
    wire funct7_5     = IR[30]; // Bit 30 para diferenciar ADD/SUB, SRL/SRA

    // Decodificación por familias de instrucción
    wire is_r_instr = (opcode == 7'b0110011);
    wire is_i_instr = (opcode == 7'b0010011);
    wire is_b_instr = (opcode == 7'b1100011);
    wire is_j_instr = (opcode == 7'b1101111);
    wire is_lui     = (opcode == 7'b0110111);
    wire is_auipc   = (opcode == 7'b0010111);
    wire is_u_instr = is_lui | is_auipc;

    // Señales específicas requeridas para GTKWave (Figura 17)
    wire is_add     = is_r_instr & (funct3 == 3'b000) & (~funct7_5); // Instrucción ADD
    wire is_addi    = is_i_instr & (funct3 == 3'b000);               // Instrucción ADDI
    wire is_load    = (opcode == 7'b0000011);                        // LB, LH, LW, LBU, LHU
    wire is_s_instr = (opcode == 7'b0100011);                        // SB, SH, SW

    // Decodificación de Saltos Condicionales (Branches)
    wire is_beq  = is_b_instr & (funct3 == 3'b000);
    wire is_bne  = is_b_instr & (funct3 == 3'b001);
    wire is_blt  = is_b_instr & (funct3 == 3'b100);
    wire is_bge  = is_b_instr & (funct3 == 3'b101);
    wire is_bltu = is_b_instr & (funct3 == 3'b110);
    wire is_bgeu = is_b_instr & (funct3 == 3'b111);

    // ------------------------------------------------------------------------
    // 3. Formatos de Inmediatos
    // ------------------------------------------------------------------------
    wire [31:0] i_imm = {{20{IR[31]}}, IR[31:20]};
    wire [31:0] s_imm = {{20{IR[31]}}, IR[31:25], IR[11:7]};
    wire [31:0] b_imm = {{20{IR[31]}}, IR[7], IR[30:25], IR[11:8], 1'b0};
    wire [31:0] u_imm = {IR[31:12], 12'b0};
    wire [31:0] j_imm = {{12{IR[31]}}, IR[19:12], IR[20], IR[30:21], 1'b0};

    // ------------------------------------------------------------------------
    // 4. Banco de Registros (Register File) y MUX de Escritura
    // ------------------------------------------------------------------------
    // Permite escribir si es Tipo R, I, J, U o Carga (LOAD), excluyendo x0
    wire wr_en = (is_r_instr | is_i_instr | is_j_instr | is_u_instr | is_load) & (rd != 5'd0);
    wire [31:0] src1_value, src2_value;
    wire [31:0] alu_out;

    // MUX de selección de datos a escribir en el Register File (Figura 16)
    wire [31:0] wdata = is_j_instr ? (pc + 32'd4) : 
                        (is_load   ? ddata_in : alu_out);

    registerfile rf (
        .clk(clk),
        .we(wr_en & state_execute2), // La escritura en el RF ocurre en state_execute2
        .waddr(rd),
        .raddr1(rs1),
        .raddr2(rs2),
        .wdata(wdata),
        .rdata1(src1_value),
        .rdata2(src2_value)
    );

    // ------------------------------------------------------------------------
    // 5. Control y Multiplexores de la ALU
    // ------------------------------------------------------------------------
    wire use_funct7_5 = (is_r_instr) | (is_i_instr & (funct3 == 3'b101));
    wire op_bit3 = use_funct7_5 & funct7_5;
    
    // Para R e I se toma {op_bit3, funct3}. Para LOAD, STORE, LUI, AUIPC se fuerza a 0000 (Suma)
    wire [3:0] alu_op = (is_r_instr | is_i_instr) ? {op_bit3, funct3} : 4'b0000;

    // MUX Operando A de la ALU
    wire [31:0] alu_a;
    assign alu_a = is_lui ? 32'd0 : (is_auipc ? pc : src1_value);

    // MUX Operando B de la ALU
    wire [31:0] imm = is_u_instr ? u_imm :
                      is_s_instr ? s_imm : i_imm; // i_imm sirve tanto para Tipo-I como para LOAD

    wire [31:0] alu_b;
    assign alu_b = (is_i_instr | is_load | is_s_instr | is_u_instr) ? imm : src2_value;

    alu cpu_alu (
        .a(alu_a),
        .b(alu_b),
        .op(alu_op),
        .out(alu_out)
    );

    // ------------------------------------------------------------------------
    // 6. Interfaz con la Memoria de Datos (DMEM)
    // ------------------------------------------------------------------------
    assign daddr     = alu_out;     // Dirección calculada por la ALU (rs1 + imm)
    assign ddata_out = src2_value;  // Dato a almacenar proviene de rs2

    // Control de lectura y escritura condicionado a los ciclos de ejecución (Execute / Execute2)
    assign dwr_en    = is_s_instr & (state_execute | state_execute2);
    assign drd_en    = is_load    & (state_execute | state_execute2);

    // ------------------------------------------------------------------------
    // 7. Lógica de Saltos y Actualización del PC
    // ------------------------------------------------------------------------
    wire cond_beq  = (src1_value == src2_value);
    wire cond_bne  = (src1_value != src2_value);
    wire cond_blt  = (src1_value < src2_value) ^ (src1_value[31] != src2_value[31]);
    wire cond_bge  = (src1_value >= src2_value) ^ (src1_value[31] != src2_value[31]);
    wire cond_bltu = (src1_value < src2_value);
    wire cond_bgeu = (src1_value >= src2_value);

    wire taken_br = (is_beq  & cond_beq)  |
                    (is_bne  & cond_bne)  |
                    (is_blt  & cond_blt)  |
                    (is_bge  & cond_bge)  |
                    (is_bltu & cond_bltu) |
                    (is_bgeu & cond_bgeu) |
                    is_j_instr;

    wire [31:0] br_tgt_pc = pc + (is_j_instr ? j_imm : b_imm);
    wire [31:0] next_pc   = taken_br ? br_tgt_pc : (pc + 32'd4);

    // Actualización del PC en el flanco de subida al finalizar el ciclo de ejecución
    always @(posedge clk) begin
        if (rst) pc <= 32'd0;
        else if (state_execute2) pc <= next_pc;
    end

endmodule

mcu_tb.v
`timescale 1ns/1ps

module tb_mcu;

    reg clk;
    reg rst;

    // Instancia del Microcontrolador
    mcu mcuuq (
        .rst(rst),
        .clk(clk)
    );

    integer i;

    initial begin
        $dumpfile("tb_mcu.vcd");
        $dumpvars(0, tb_mcu);

        // Volcar las 32 posiciones del banco de registros
        for (i = 0; i < 32; i = i + 1)
            $dumpvars(0, mcuuq.cpu.rf.mem[i]);

        clk = 0;
        rst = 1;

        #93;
        rst = 0; // Se libera el reset a los 93ns

        #240; // Simulación durante 60 ciclos de reloj
        #16;
        $finish;
    end

    // Reloj con período de 4ns (2ns en alto / 2ns en bajo)
    always begin
        #2 clk = !clk;
    end

endmodule

tb_mcu.vcd
$date
	Wed Oct  7 23:18:54 2026
$end
$version
	Icarus Verilog
$end
$timescale
	1ps
$end
$scope module tb_mcu $end
$var reg 1 ! clk $end
$var reg 1 " rst $end
$var integer 32 # i [31:0] $end
$scope module mcuuq $end
$var wire 1 ! clk $end
$var wire 1 " rst $end
$var wire 32 $ instr [31:0] $end
$var wire 32 % iaddr [31:0] $end
$var wire 1 & dwr_en $end
$var wire 1 ' drd_en $end
$var wire 32 ( ddata_out [31:0] $end
$var wire 32 ) ddata_in [31:0] $end
$var wire 32 * daddr [31:0] $end
$scope module DMEM $end
$var wire 10 + addr [9:0] $end
$var wire 1 ! clk $end
$var wire 1 & wr_en $end
$var wire 32 , wr_data [31:0] $end
$var wire 1 ' rd_en $end
$var wire 32 - rd_data [31:0] $end
$var parameter 32 . WORDS $end
$var reg 32 / rd_reg [31:0] $end
$upscope $end
$scope module IMEM $end
$var wire 12 0 addr [11:0] $end
$var wire 1 ! clk $end
$var reg 32 1 data [31:0] $end
$upscope $end
$scope module cpu $end
$var wire 1 ! clk $end
$var wire 1 2 cond_bge $end
$var wire 1 3 cond_blt $end
$var wire 32 4 daddr [31:0] $end
$var wire 32 5 ddata_in [31:0] $end
$var wire 32 6 ddata_out [31:0] $end
$var wire 1 ' drd_en $end
$var wire 1 & dwr_en $end
$var wire 32 7 iaddr [31:0] $end
$var wire 32 8 instr [31:0] $end
$var wire 1 9 is_add $end
$var wire 1 : is_addi $end
$var wire 1 ; is_beq $end
$var wire 1 < is_bge $end
$var wire 1 = is_bgeu $end
$var wire 1 > is_blt $end
$var wire 1 ? is_bltu $end
$var wire 1 @ is_bne $end
$var wire 1 A is_u_instr $end
$var wire 1 B op_bit3 $end
$var wire 1 " rst $end
$var wire 1 C taken_br $end
$var wire 1 D use_funct7_5 $end
$var wire 1 E wr_en $end
$var wire 32 F wdata [31:0] $end
$var wire 32 G u_imm [31:0] $end
$var wire 32 H src2_value [31:0] $end
$var wire 32 I src1_value [31:0] $end
$var wire 32 J s_imm [31:0] $end
$var wire 5 K rs2 [4:0] $end
$var wire 5 L rs1 [4:0] $end
$var wire 5 M rd [4:0] $end
$var wire 7 N opcode [6:0] $end
$var wire 32 O next_pc [31:0] $end
$var wire 32 P j_imm [31:0] $end
$var wire 1 Q is_s_instr $end
$var wire 1 R is_r_instr $end
$var wire 1 S is_lui $end
$var wire 1 T is_load $end
$var wire 1 U is_j_instr $end
$var wire 1 V is_i_instr $end
$var wire 1 W is_b_instr $end
$var wire 1 X is_auipc $end
$var wire 32 Y imm [31:0] $end
$var wire 32 Z i_imm [31:0] $end
$var wire 1 [ funct7_5 $end
$var wire 7 \ funct7 [6:0] $end
$var wire 3 ] funct3 [2:0] $end
$var wire 1 ^ cond_bne $end
$var wire 1 _ cond_bltu $end
$var wire 1 ` cond_bgeu $end
$var wire 1 a cond_beq $end
$var wire 32 b br_tgt_pc [31:0] $end
$var wire 32 c b_imm [31:0] $end
$var wire 32 d alu_out [31:0] $end
$var wire 4 e alu_op [3:0] $end
$var wire 32 f alu_b [31:0] $end
$var wire 32 g alu_a [31:0] $end
$var reg 32 h IR [31:0] $end
$var reg 32 i pc [31:0] $end
$var reg 1 j state_decode $end
$var reg 1 k state_execute $end
$var reg 1 l state_execute2 $end
$var reg 1 m state_fetch $end
$scope module cpu_alu $end
$var wire 32 n a [31:0] $end
$var wire 32 o b [31:0] $end
$var wire 4 p op [3:0] $end
$var wire 32 q sltu_result [31:0] $end
$var wire 32 r slt_result [31:0] $end
$var wire 5 s shamt [4:0] $end
$var wire 64 t a_ext [63:0] $end
$var reg 32 u out [31:0] $end
$upscope $end
$scope module rf $end
$var wire 1 ! clk $end
$var wire 5 v raddr1 [4:0] $end
$var wire 5 w raddr2 [4:0] $end
$var wire 5 x waddr [4:0] $end
$var wire 32 y wdata [31:0] $end
$var wire 1 z we $end
$var wire 32 { rdata2 [31:0] $end
$var wire 32 | rdata1 [31:0] $end
$var integer 32 } k [31:0] $end
$upscope $end
$upscope $end
$upscope $end
$upscope $end
$scope module tb_mcu $end
$scope module mcuuq $end
$scope module cpu $end
$scope module rf $end
$var reg 32 ~ \mem[0] [31:0] $end
$upscope $end
$upscope $end
$upscope $end
$upscope $end
$scope module tb_mcu $end
$scope module mcuuq $end
$scope module cpu $end
$scope module rf $end
$var reg 32 !" \mem[1] [31:0] $end
$upscope $end
$upscope $end
$upscope $end
$upscope $end
$scope module tb_mcu $end
$scope module mcuuq $end
$scope module cpu $end
$scope module rf $end
$var reg 32 "" \mem[2] [31:0] $end
$upscope $end
$upscope $end
$upscope $end
$upscope $end
$scope module tb_mcu $end
$scope module mcuuq $end
$scope module cpu $end
$scope module rf $end
$var reg 32 #" \mem[3] [31:0] $end
$upscope $end
$upscope $end
$upscope $end
$upscope $end
$scope module tb_mcu $end
$scope module mcuuq $end
$scope module cpu $end
$scope module rf $end
$var reg 32 $" \mem[4] [31:0] $end
$upscope $end
$upscope $end
$upscope $end
$upscope $end
$scope module tb_mcu $end
$scope module mcuuq $end
$scope module cpu $end
$scope module rf $end
$var reg 32 %" \mem[5] [31:0] $end
$upscope $end
$upscope $end
$upscope $end
$upscope $end
$scope module tb_mcu $end
$scope module mcuuq $end
$scope module cpu $end
$scope module rf $end
$var reg 32 &" \mem[6] [31:0] $end
$upscope $end
$upscope $end
$upscope $end
$upscope $end
$scope module tb_mcu $end
$scope module mcuuq $end
$scope module cpu $end
$scope module rf $end
$var reg 32 '" \mem[7] [31:0] $end
$upscope $end
$upscope $end
$upscope $end
$upscope $end
$scope module tb_mcu $end
$scope module mcuuq $end
$scope module cpu $end
$scope module rf $end
$var reg 32 (" \mem[8] [31:0] $end
$upscope $end
$upscope $end
$upscope $end
$upscope $end
$scope module tb_mcu $end
$scope module mcuuq $end
$scope module cpu $end
$scope module rf $end
$var reg 32 )" \mem[9] [31:0] $end
$upscope $end
$upscope $end
$upscope $end
$upscope $end
$scope module tb_mcu $end
$scope module mcuuq $end
$scope module cpu $end
$scope module rf $end
$var reg 32 *" \mem[10] [31:0] $end
$upscope $end
$upscope $end
$upscope $end
$upscope $end
$scope module tb_mcu $end
$scope module mcuuq $end
$scope module cpu $end
$scope module rf $end
$var reg 32 +" \mem[11] [31:0] $end
$upscope $end
$upscope $end
$upscope $end
$upscope $end
$scope module tb_mcu $end
$scope module mcuuq $end
$scope module cpu $end
$scope module rf $end
$var reg 32 ," \mem[12] [31:0] $end
$upscope $end
$upscope $end
$upscope $end
$upscope $end
$scope module tb_mcu $end
$scope module mcuuq $end
$scope module cpu $end
$scope module rf $end
$var reg 32 -" \mem[13] [31:0] $end
$upscope $end
$upscope $end
$upscope $end
$upscope $end
$scope module tb_mcu $end
$scope module mcuuq $end
$scope module cpu $end
$scope module rf $end
$var reg 32 ." \mem[14] [31:0] $end
$upscope $end
$upscope $end
$upscope $end
$upscope $end
$scope module tb_mcu $end
$scope module mcuuq $end
$scope module cpu $end
$scope module rf $end
$var reg 32 /" \mem[15] [31:0] $end
$upscope $end
$upscope $end
$upscope $end
$upscope $end
$scope module tb_mcu $end
$scope module mcuuq $end
$scope module cpu $end
$scope module rf $end
$var reg 32 0" \mem[16] [31:0] $end
$upscope $end
$upscope $end
$upscope $end
$upscope $end
$scope module tb_mcu $end
$scope module mcuuq $end
$scope module cpu $end
$scope module rf $end
$var reg 32 1" \mem[17] [31:0] $end
$upscope $end
$upscope $end
$upscope $end
$upscope $end
$scope module tb_mcu $end
$scope module mcuuq $end
$scope module cpu $end
$scope module rf $end
$var reg 32 2" \mem[18] [31:0] $end
$upscope $end
$upscope $end
$upscope $end
$upscope $end
$scope module tb_mcu $end
$scope module mcuuq $end
$scope module cpu $end
$scope module rf $end
$var reg 32 3" \mem[19] [31:0] $end
$upscope $end
$upscope $end
$upscope $end
$upscope $end
$scope module tb_mcu $end
$scope module mcuuq $end
$scope module cpu $end
$scope module rf $end
$var reg 32 4" \mem[20] [31:0] $end
$upscope $end
$upscope $end
$upscope $end
$upscope $end
$scope module tb_mcu $end
$scope module mcuuq $end
$scope module cpu $end
$scope module rf $end
$var reg 32 5" \mem[21] [31:0] $end
$upscope $end
$upscope $end
$upscope $end
$upscope $end
$scope module tb_mcu $end
$scope module mcuuq $end
$scope module cpu $end
$scope module rf $end
$var reg 32 6" \mem[22] [31:0] $end
$upscope $end
$upscope $end
$upscope $end
$upscope $end
$scope module tb_mcu $end
$scope module mcuuq $end
$scope module cpu $end
$scope module rf $end
$var reg 32 7" \mem[23] [31:0] $end
$upscope $end
$upscope $end
$upscope $end
$upscope $end
$scope module tb_mcu $end
$scope module mcuuq $end
$scope module cpu $end
$scope module rf $end
$var reg 32 8" \mem[24] [31:0] $end
$upscope $end
$upscope $end
$upscope $end
$upscope $end
$scope module tb_mcu $end
$scope module mcuuq $end
$scope module cpu $end
$scope module rf $end
$var reg 32 9" \mem[25] [31:0] $end
$upscope $end
$upscope $end
$upscope $end
$upscope $end
$scope module tb_mcu $end
$scope module mcuuq $end
$scope module cpu $end
$scope module rf $end
$var reg 32 :" \mem[26] [31:0] $end
$upscope $end
$upscope $end
$upscope $end
$upscope $end
$scope module tb_mcu $end
$scope module mcuuq $end
$scope module cpu $end
$scope module rf $end
$var reg 32 ;" \mem[27] [31:0] $end
$upscope $end
$upscope $end
$upscope $end
$upscope $end
$scope module tb_mcu $end
$scope module mcuuq $end
$scope module cpu $end
$scope module rf $end
$var reg 32 <" \mem[28] [31:0] $end
$upscope $end
$upscope $end
$upscope $end
$upscope $end
$scope module tb_mcu $end
$scope module mcuuq $end
$scope module cpu $end
$scope module rf $end
$var reg 32 =" \mem[29] [31:0] $end
$upscope $end
$upscope $end
$upscope $end
$upscope $end
$scope module tb_mcu $end
$scope module mcuuq $end
$scope module cpu $end
$scope module rf $end
$var reg 32 >" \mem[30] [31:0] $end
$upscope $end
$upscope $end
$upscope $end
$upscope $end
$scope module tb_mcu $end
$scope module mcuuq $end
$scope module cpu $end
$scope module rf $end
$var reg 32 ?" \mem[31] [31:0] $end
$upscope $end
$upscope $end
$upscope $end
$upscope $end
$enddefinitions $end
$comment Show the parameter values. $end
$dumpall
b10000000000 .
$end
#0
$dumpvars
b0 ?"
b0 >"
b0 ="
b0 <"
b0 ;"
b0 :"
b0 9"
b0 8"
b0 7"
b0 6"
b0 5"
b0 4"
b0 3"
b0 2"
b0 1"
b0 0"
b0 /"
b0 ."
b0 -"
b0 ,"
b0 +"
b0 *"
b0 )"
b0 ("
b0 '"
b0 &"
b0 %"
b0 $"
b0 #"
b0 ""
b0 !"
b0 ~
b100000 }
bx |
bx {
0z
bx y
bx x
bx w
bx v
b0 u
bx t
bx s
b0x r
b0x q
bx p
bx o
bx n
1m
0l
0k
0j
bx i
bx h
bx g
bx f
bx e
b0 d
bx0 c
bx b
xa
x`
x_
x^
bx ]
bx \
x[
bx Z
bx Y
xX
xW
xV
xU
xT
xS
xR
xQ
bx0 P
bx O
bx N
bx M
bx L
bx K
bx J
bx I
bx H
bx000000000000 G
bx F
xE
xD
xC
xB
xA
x@
x?
x>
x=
x<
x;
x:
x9
bx 8
bx 7
bx 6
bz 5
b0 4
x3
x2
bx 1
bx 0
bx /
bz -
bx ,
b0 +
b0 *
bz )
bx (
0'
0&
bx %
bx $
b100000 #
1"
0!
$end
#2000
0C
12
03
b0 r
b100 O
b0 s
b0 q
b0 b
b0 t
b0 e
b0 p
b0 f
b0 o
09
b0 c
b0 Y
b0 P
0D
b0 F
b0 y
b0 g
b0 n
0A
0E
0:
0;
0@
0>
0<
0?
0=
1`
0_
0^
1a
b0 I
b0 |
b0 (
b0 ,
b0 6
b0 H
b0 {
0B
b0 Z
b0 J
b0 G
0R
0V
0W
0U
0S
0X
0T
0Q
b0 N
b0 M
b0 x
b0 ]
b0 L
b0 v
b0 K
b0 w
b0 \
0[
b0 0
b0 h
b0 %
b0 7
b0 i
1!
#4000
0!
#6000
b110000000000001010010011 $
b110000000000001010010011 1
b110000000000001010010011 8
1!
#8000
0!
#10000
1!
#12000
0!
#14000
1!
#16000
0!
#18000
1!
#20000
0!
#22000
1!
#24000
0!
#26000
1!
#28000
0!
#30000
1!
#32000
0!
#34000
1!
#36000
0!
#38000
1!
#40000
0!
#42000
1!
#44000
0!
#46000
1!
#48000
0!
#50000
1!
#52000
0!
#54000
1!
#56000
0!
#58000
1!
#60000
0!
#62000
1!
#64000
0!
#66000
1!
#68000
0!
#70000
1!
#72000
0!
#74000
1!
#76000
0!
#78000
1!
#80000
0!
#82000
1!
#84000
0!
#86000
1!
#88000
0!
#90000
1!
#92000
0!
#93000
0"
#94000
b1100 F
b1100 y
b11 +
b1 r
b1100 *
b1100 4
b1100 d
b1100 u
b1100 s
b1 q
1E
b1100 f
b1100 o
b1100 Y
b100000000100 b
b100000000100 c
b1100 P
1:
b1100 Z
b101 J
b110000000000000000000000 G
1V
b10011 N
b101 M
b101 x
b1100 K
b1100 w
b110000000000001010010011 h
1!
#96000
1j
0m
0!
#98000
1!
#100000
1k
0j
0!
#102000
1!
#104000
1z
1l
0k
0!
#106000
b1000 O
b1 0
b1100 %"
b100000001000 b
b100 %
b100 7
b100 i
1!
#108000
0z
0l
1m
0!
#110000
b10100000010100000100011 $
b10100000010100000100011 1
b10100000010100000100011 8
1!
#112000
1j
0m
0!
#114000
1!
#116000
1k
0j
0!
#118000
1!
#120000
1z
1l
0k
0!
#122000
b1100 O
b10 0
b1100 %"
b100000001100 b
b1000 %
b1000 7
b1000 i
1!
#124000
0z
0l
1m
0!
#126000
b10000 F
b10000 y
0E
b100 +
b10000 *
b10000 4
b10000 d
b10000 u
b10000 s
b10000 f
b10000 o
02
13
b11000 b
b10000 Y
0`
1_
1^
0a
b1100 (
b1100 ,
b1100 6
b1100 H
b1100 {
b10000 c
b10100000000100 P
0:
b101 Z
b10000 J
b10100000010000000000000 G
0V
1Q
b100011 N
b10000 M
b10000 x
b10 ]
b101 K
b101 w
b1011100000000001010010011 $
b1011100000000001010010011 1
b1011100000000001010010011 8
b10100000010100000100011 h
1!
#128000
1j
0m
0!
#130000
1!
#132000
1&
1k
0j
0!
#134000
1!
#136000
1l
0k
0!
#138000
b10000 O
b11 0
b11100 b
b1100 %
b1100 7
b1100 i
1!
#140000
0&
0l
1m
0!
#142000
b10111 F
b10111 y
1E
b101 +
b1 r
b10111 *
b10111 4
b10111 d
b10111 u
b10111 s
b1 q
b10111 f
b10111 o
12
03
b100000010000 b
b10111 Y
1`
0_
0^
1a
b0 (
b0 ,
b0 6
b0 H
b0 {
b100000000100 c
b100000010110 P
1:
b10111 Z
b101 J
b1011100000000000000000000 G
1V
0Q
b10011 N
b101 M
b101 x
b0 ]
b10111 K
b10111 w
b10100000010101000100011 $
b10100000010101000100011 1
b10100000010101000100011 8
b1011100000000001010010011 h
1!
#144000
1j
0m
0!
#146000
1!
#148000
1k
0j
0!
#150000
1!
#152000
1z
1l
0k
0!
#154000
b10100 O
b100 0
b10111 %"
b100000010100 b
b10000 %
b10000 7
b10000 i
1!
#156000
0z
0l
1m
0!
#158000
b10100 F
b10100 y
0E
b10100 *
b10100 4
b10100 d
b10100 u
b10100 s
b10100 f
b10100 o
02
13
b100100 b
b10100 Y
0`
1_
1^
0a
b10111 (
b10111 ,
b10111 6
b10111 H
b10111 {
b10100 c
b10100000000100 P
0:
b101 Z
b10100 J
b10100000010000000000000 G
0V
1Q
b100011 N
b10100 M
b10100 x
b10 ]
b101 K
b101 w
b1000000000010001010000011 $
b1000000000010001010000011 1
b1000000000010001010000011 8
b10100000010101000100011 h
1!
#160000
1j
0m
0!
#162000
1!
#164000
1&
1k
0j
0!
#166000
1!
#168000
1l
0k
0!
#170000
b11000 O
b101 0
b101000 b
b10100 %
b10100 7
b10100 i
1!
#172000
0&
0l
1m
0!
#174000
b100 +
b1 r
b10000 *
b10000 4
b10000 d
b10000 u
b10000 s
b1 q
b10000 f
b10000 o
12
03
b100000011000 b
bz F
bz y
1E
b10000 Y
1`
0_
0^
1a
b0 (
b0 ,
b0 6
b0 H
b0 {
b100000000100 c
b10000000010000 P
b10000 Z
b101 J
b1000000000010000000000000 G
1T
0Q
b11 N
b101 M
b101 x
b10000 K
b10000 w
b1010000000010001100000011 $
b1010000000010001100000011 1
b1010000000010001100000011 8
b1000000000010001010000011 h
1!
#176000
1j
0m
0!
#178000
1!
#180000
bx F
bx y
bx )
bx -
bx 5
1'
1k
0j
0!
#182000
b1100 F
b1100 y
b1100 )
b1100 -
b1100 5
b1100 /
1!
#184000
1z
1l
0k
0!
#186000
b11100 O
b110 0
b1100 %"
b100000011100 b
b11000 %
b11000 7
b11000 i
1!
#188000
bz F
bz y
bz )
bz -
bz 5
0'
0z
0l
1m
0!
#190000
b101 +
b10100 *
b10100 4
b10100 d
b10100 u
b10100 s
b10100 f
b10100 o
b10100 Y
b11110 b
b110 c
b10000000010100 P
b10100 Z
b110 J
b1010000000010000000000000 G
b110 M
b110 x
b10100 K
b10100 w
b11000101000001110110011 $
b11000101000001110110011 1
b11000101000001110110011 8
b1010000000010001100000011 h
1!
#192000
1j
0m
0!
#194000
1!
#196000
b1100 F
b1100 y
b1100 )
b1100 -
b1100 5
1'
1k
0j
0!
#198000
b10111 F
b10111 y
b10111 )
b10111 -
b10111 5
b10111 /
1!
#200000
1z
1l
0k
0!
#202000
b100000 O
b111 0
b10111 &"
b100010 b
b11100 %
b11100 7
b11100 i
1!
#204000
bz F
bz y
bz )
bz -
bz 5
0'
0z
0l
1m
0!
#206000
b1000 +
b10111 s
b100011 *
b100011 4
b100011 d
b100011 u
b1100 t
b10111 f
b10111 o
b1100 g
b1100 n
02
13
b110 Y
b100000100010 b
b100011 F
b100011 y
1E
19
0`
1_
b10111 (
b10111 ,
b10111 6
b10111 H
b10111 {
b100000000110 c
b101000000000000110 P
1D
1^
0a
b1100 I
b1100 |
b110 Z
b111 J
b11000101000000000000000 G
1R
0T
b110011 N
b111 M
b111 x
b0 ]
b101 L
b101 v
b110 K
b110 w
b11100000010110000100011 $
b11100000010110000100011 1
b11100000010110000100011 8
b11000101000001110110011 h
1!
#208000
1j
0m
0!
#210000
1!
#212000
1k
0j
0!
#214000
1!
