rom4096x32.v
module rom4096x32 (
    input wire [11:0] addr, 
    output reg [31:0] data  
);
    // Memoria RAM/ROM de 4096 posiciones de 32 bits
    reg [31:0] mem [0:4095];

    // Inicialización cargando el archivo hex
    initial begin
        // Lee el archivo hexadecimal y lo carga en la memoria
        $readmemh("test_program.hex", mem);
    end

    always @(*) begin
        data = mem[addr];
    end
endmodule

alu.v
module alu (
    input wire [31:0] a,
    input wire [31:0] b,
    input wire [3:0] op, // Ampliado a 4 bits para soportar todas las operaciones
    output reg [31:0] out
);

  
    // PASO 3: Cálculos previos de la ALU

    wire [4:0]  shamt;
    wire [63:0] a_ext;
    wire [31:0] sltu_result;
    wire [31:0] slt_result;

    // Valor del shift
    assign shamt = b[4:0];

    // Extensión de signo de la entrada 'a' para 64 bits (útil para SRA)
    assign a_ext = { {32{a[31]}}, a };

    // Valor obtenido por set if less than unsigned (sltu)
    assign sltu_result = {31'b0, a < b};

    // Valor obtenido por set if less than (signed)
    assign slt_result = (a[31] == b[31]) ? sltu_result : {31'b0, a[31]};
   



    // PASO 4 (Parte 1): Ampliar el MUX de la ALU
  
    always @(*) begin
        case (op)
            4'b0000: out = a + b;           // ADD / ADDI / LUI / AUIPC (Suman)
            4'b1000: out = a - b;           // SUB
            4'b0001: out = a << shamt;      // SLL / SLLI
            4'b0010: out = slt_result;      // SLT / SLTI
            4'b0011: out = sltu_result;     // SLTU / SLTIU
            4'b0100: out = a ^ b;           // XOR / XORI
            4'b0101: out = a >> shamt;      // SRL / SRLI
            4'b1101: out = a_ext >> shamt;  // SRA / SRAI (Aritmético usa a_ext)
            4'b0110: out = a | b;           // OR / ORI
            4'b0111: out = a & b;           // AND / ANDI
            default: out = 32'd0;
        endcase
    end
    
endmodule

registerfile.v
module registerfile (
    input wire clk,
    input wire we,
    input wire [4:0] waddr,
    input wire [4:0] raddr1,
    input wire [4:0] raddr2,
    input wire [31:0] wdata,
    output wire [31:0] rdata1,
    output wire [31:0] rdata2
);
    reg [31:0] mem [0:31];

    // Inicialización a 0 de todos los registros para evitar x (rojo) en la simulación
    integer k;
    initial begin
        for (k = 0; k < 32; k = k + 1) begin
            mem[k] = 32'd0;
        end
    end

    // Escritura sincrónica (el registro x0 siempre se mantiene en 0)
    always @(posedge clk) begin
        if (we && (waddr != 5'd0)) begin
            mem[waddr] <= wdata;
        end
    end

    // Lectura combinacional
    assign rdata1 = (raddr1 == 5'd0) ? 32'd0 : mem[raddr1];
    assign rdata2 = (raddr2 == 5'd0) ? 32'd0 : mem[raddr2];

endmodule

riscv.v
module riscv (
    input wire clk,
    input wire rst,
    input wire [31:0] instr,
    output wire [31:0] iaddr,
    output wire [31:0] daddr,
    input wire [31:0] ddata_in,
    output wire [31:0] ddata_out,
    output wire dwr_en,
    output wire drd_en
);

    reg [31:0] pc;
    assign iaddr = pc;

    reg state_fetch, state_decode, state_execute;

    always @(negedge clk) begin
        if (rst) begin
            state_fetch   <= 1'b1;
            state_decode  <= 1'b0;
            state_execute <= 1'b0;
        end else begin
            state_fetch   <= state_execute;
            state_decode  <= state_fetch;
            state_execute <= state_decode;
        end
    end

    reg [31:0] IR;
    always @(posedge clk) begin
        if (rst) IR <= 32'd0;
        else if (state_fetch) IR <= instr;
    end

    wire [6:0] opcode = IR[6:0];
    wire [4:0] rd     = IR[11:7];
    wire [2:0] funct3 = IR[14:12];
    wire [4:0] rs1    = IR[19:15];
    wire [4:0] rs2    = IR[24:20];
    wire [6:0] funct7 = IR[31:25];


    // PASO 1: Decodificación de instrucciones
    wire is_r_instr = (opcode == 7'b0110011);
    wire is_i_instr = (opcode == 7'b0010011);
    wire is_b_instr = (opcode == 7'b1100011);
    wire is_j_instr = (opcode == 7'b1101111);
    
    // Nuevas instrucciones tipo U
    wire is_lui   = (opcode == 7'b0110111);
    wire is_auipc = (opcode == 7'b0010111);
    wire is_u_instr = is_lui | is_auipc;

    // Bit 5 de funct7 para diferenciar instrucciones (ej. SRL vs SRA, ADD vs SUB)
    wire funct7_5 = IR[30]; 
    

    wire is_beq  = is_b_instr & (funct3 == 3'b000);
    wire is_bne  = is_b_instr & (funct3 == 3'b001);
    wire is_blt  = is_b_instr & (funct3 == 3'b100);
    wire is_bge  = is_b_instr & (funct3 == 3'b101);
    wire is_bltu = is_b_instr & (funct3 == 3'b110);
    wire is_bgeu = is_b_instr & (funct3 == 3'b111);

    // Formatos de Inmediatos
    wire [31:0] i_imm = {{20{IR[31]}}, IR[31:20]};
    wire [31:0] b_imm = {{20{IR[31]}}, IR[7], IR[30:25], IR[11:8], 1'b0};
    wire [31:0] j_imm = {{12{IR[31]}}, IR[19:12], IR[20], IR[30:21], 1'b0};
    
    // Inmediato tipo U: Desplazado 12 bits a la izquierda como dicta la guía
    wire [31:0] u_imm = {IR[31:12], 12'b0};

    // Habilitar escritura en registro (ahora incluye is_u_instr)
    wire wr_en = (is_r_instr | is_i_instr | is_j_instr | is_u_instr) & (rd != 5'd0);
    wire [31:0] src1_value, src2_value;
    wire [31:0] alu_out;
    wire [31:0] wdata = is_j_instr ? (pc + 32'd4) : alu_out;

    registerfile rf (
        .clk(clk),
        .we(wr_en & state_execute),
        .waddr(rd),
        .raddr1(rs1),
        .raddr2(rs2),
        .wdata(wdata),
        .rdata1(src1_value),
        .rdata2(src2_value)
    );

   
    // PASO 2: Generar la señal 'op' de la ALU

    // El bit más significativo del op (op[3]) depende de funct7_5.
    // Solo aplica para tipo R y para la instrucción SRAI (tipo I, funct3=101).
    wire use_funct7_5 = (is_r_instr) | (is_i_instr & (funct3 == 3'b101));
    wire op_bit3 = use_funct7_5 & funct7_5;
    
    // Si es R o I, pasamos {op_bit3, funct3}. Si es LUI/AUIPC pasa 0000 (Suma).
    wire [3:0] alu_op = (is_r_instr | is_i_instr) ? {op_bit3, funct3} : 4'b0000;
  


    // PASO 4 (Parte 2): Multiplexores A y B de la ALU

    wire [31:0] alu_a;
    wire [31:0] alu_b;

    // Si es LUI, A=0. Si es AUIPC, A=PC. De lo contrario, A=src1_value.
    assign alu_a = is_lui ? 32'd0 : (is_auipc ? pc : src1_value);

    // Si es U-Type usa u_imm. Si es I-Type usa i_imm. De lo contrario usa src2_value.
    wire [31:0] imm = is_u_instr ? u_imm : i_imm;
    assign alu_b = (is_i_instr | is_u_instr) ? imm : src2_value;

    alu cpu_alu (
        .a(alu_a),
        .b(alu_b),
        .op(alu_op),
        .out(alu_out)
    );
    

    wire cond_beq  = (src1_value == src2_value);
    wire cond_bne  = (src1_value != src2_value);
    wire cond_blt  = (src1_value < src2_value) ^ (src1_value[31] != src2_value[31]);
    wire cond_bge  = (src1_value >= src2_value) ^ (src1_value[31] != src2_value[31]);
    wire cond_bltu = (src1_value < src2_value);
    wire cond_bgeu = (src1_value >= src2_value);

    wire taken_br = (is_beq  & cond_beq)  |
                    (is_bne  & cond_bne)  |
                    (is_blt  & cond_blt)  |
                    (is_bge  & cond_bge)  |
                    (is_bltu & cond_bltu) |
                    (is_bgeu & cond_bgeu) |
                    is_j_instr;

    wire [31:0] br_tgt_pc = pc + (is_j_instr ? j_imm : b_imm);
    wire [31:0] next_pc   = taken_br ? br_tgt_pc : (pc + 32'd4);

    always @(posedge clk) begin
        if (rst) pc <= 32'd0;
        else if (state_execute) pc <= next_pc;
    end

    assign daddr     = 32'd0;
    assign ddata_out = 32'd0;
    assign dwr_en    = 1'b0;
    assign drd_en    = 1'b0;

endmodule

mcu.v
module mcu (
    input wire clk, // Reloj del microcontrolador
    input wire rst  // Reset del microcontrolador
);
    // Buses con la memoria de programa (IMEM)
    wire [31:0] instr; // Instrucción leída
    wire [31:0] iaddr; // Dirección del PC emitida por la CPU

    // Buses con la memoria de datos (DMEM)
    wire [31:0] daddr;     // Dirección en la DMEM
    wire [31:0] ddata_in;  // Bus de datos DMEM (entrada)
    wire [31:0] ddata_out; // Bus de datos DMEM (salida)
    wire dwr_en;           // Señal de escritura en DMEM
    wire drd_en;           // Señal de lectura en DMEM

    // Instancia de la CPU RISC-V
    riscv cpu (
        .rst(rst),
        .clk(clk),
        .instr(instr),
        .iaddr(iaddr),
        .daddr(daddr),
        .ddata_in(ddata_in),
        .ddata_out(ddata_out),
        .dwr_en(dwr_en),
        .drd_en(drd_en)
    );

    // Instancia de la Memoria ROM de programa
    rom4096x32 IMEM (
        .data(instr),
        .addr(iaddr[13:2]) 
    );

endmodule

mcu_tb.v
`timescale 1ns/1ps

module tb_mcu;

    reg clk;
    reg rst;

    // Instancia del Microcontrolador
    mcu mcuuq (
        .rst(rst),
        .clk(clk)
    );

    integer i;

    initial begin
        $dumpfile("tb_mcu.vcd");
        $dumpvars(0, tb_mcu);

        // Volcar las 32 posiciones del banco de registros para verlas en GTKWave
        for (i = 0; i < 32; i = i + 1)
            $dumpvars(0, mcuuq.cpu.rf.mem[i]);
            
        // NUEVO: Monitorear en consola las señales clave del proceso de fetch y ejecución
        $monitor("Tiempo=%0t | rst=%b | PC=%h | Instruccion leida=%h | Registro x12=%h", 
                 $time, rst, mcuuq.cpu.pc, mcuuq.IMEM.data, mcuuq.cpu.rf.mem[12]);

        clk = 0;
        rst = 1;

        #93;
        rst = 0; // Se libera el reset a los 93ns

        #500; // Damos suficiente tiempo para que se ejecuten todas las instrucciones
        $finish;
    end

    // Reloj con período de 4ns (2ns en alto / 2ns en bajo)
    always begin
        #2 clk = !clk;
    end

endmodule

tb_mcu.vcd
$date
	Tue Oct  6 02:55:44 2026
$end
$version
	Icarus Verilog
$end
$timescale
	1ps
$end
$scope module tb_mcu $end
$var reg 1 ! clk $end
$var reg 1 " rst $end
$var integer 32 # i [31:0] $end
$scope module mcuuq $end
$var wire 1 ! clk $end
$var wire 32 $ daddr [31:0] $end
$var wire 32 % ddata_in [31:0] $end
$var wire 32 & ddata_out [31:0] $end
$var wire 1 ' drd_en $end
$var wire 1 ( dwr_en $end
$var wire 1 " rst $end
$var wire 32 ) instr [31:0] $end
$var wire 32 * iaddr [31:0] $end
$scope module IMEM $end
$var wire 12 + addr [11:0] $end
$var reg 32 , data [31:0] $end
$upscope $end
$scope module cpu $end
$var wire 1 ! clk $end
$var wire 1 - cond_bge $end
$var wire 1 . cond_blt $end
$var wire 32 / daddr [31:0] $end
$var wire 32 0 ddata_in [31:0] $end
$var wire 32 1 ddata_out [31:0] $end
$var wire 1 ' drd_en $end
$var wire 1 ( dwr_en $end
$var wire 32 2 iaddr [31:0] $end
$var wire 32 3 instr [31:0] $end
$var wire 1 4 is_beq $end
$var wire 1 5 is_bge $end
$var wire 1 6 is_bgeu $end
$var wire 1 7 is_blt $end
$var wire 1 8 is_bltu $end
$var wire 1 9 is_bne $end
$var wire 1 : is_u_instr $end
$var wire 1 ; op_bit3 $end
$var wire 1 " rst $end
$var wire 1 < taken_br $end
$var wire 1 = use_funct7_5 $end
$var wire 1 > wr_en $end
$var wire 32 ? wdata [31:0] $end
$var wire 32 @ u_imm [31:0] $end
$var wire 32 A src2_value [31:0] $end
$var wire 32 B src1_value [31:0] $end
$var wire 5 C rs2 [4:0] $end
$var wire 5 D rs1 [4:0] $end
$var wire 5 E rd [4:0] $end
$var wire 7 F opcode [6:0] $end
$var wire 32 G next_pc [31:0] $end
$var wire 32 H j_imm [31:0] $end
$var wire 1 I is_r_instr $end
$var wire 1 J is_lui $end
$var wire 1 K is_j_instr $end
$var wire 1 L is_i_instr $end
$var wire 1 M is_b_instr $end
$var wire 1 N is_auipc $end
$var wire 32 O imm [31:0] $end
$var wire 32 P i_imm [31:0] $end
$var wire 1 Q funct7_5 $end
$var wire 7 R funct7 [6:0] $end
$var wire 3 S funct3 [2:0] $end
$var wire 1 T cond_bne $end
$var wire 1 U cond_bltu $end
$var wire 1 V cond_bgeu $end
$var wire 1 W cond_beq $end
$var wire 32 X br_tgt_pc [31:0] $end
$var wire 32 Y b_imm [31:0] $end
$var wire 32 Z alu_out [31:0] $end
$var wire 4 [ alu_op [3:0] $end
$var wire 32 \ alu_b [31:0] $end
$var wire 32 ] alu_a [31:0] $end
$var reg 32 ^ IR [31:0] $end
$var reg 32 _ pc [31:0] $end
$var reg 1 ` state_decode $end
$var reg 1 a state_execute $end
$var reg 1 b state_fetch $end
$scope module cpu_alu $end
$var wire 32 c a [31:0] $end
$var wire 32 d b [31:0] $end
$var wire 4 e op [3:0] $end
$var wire 32 f sltu_result [31:0] $end
$var wire 32 g slt_result [31:0] $end
$var wire 5 h shamt [4:0] $end
$var wire 64 i a_ext [63:0] $end
$var reg 32 j out [31:0] $end
$upscope $end
$scope module rf $end
$var wire 1 ! clk $end
$var wire 5 k raddr1 [4:0] $end
$var wire 5 l raddr2 [4:0] $end
$var wire 5 m waddr [4:0] $end
$var wire 32 n wdata [31:0] $end
$var wire 1 o we $end
$var wire 32 p rdata2 [31:0] $end
$var wire 32 q rdata1 [31:0] $end
$var integer 32 r k [31:0] $end
$upscope $end
$upscope $end
$upscope $end
$upscope $end
$scope module tb_mcu $end
$scope module mcuuq $end
$scope module cpu $end
$scope module rf $end
$var reg 32 s \mem[0] [31:0] $end
$upscope $end
$upscope $end
$upscope $end
$upscope $end
$scope module tb_mcu $end
$scope module mcuuq $end
$scope module cpu $end
$scope module rf $end
$var reg 32 t \mem[1] [31:0] $end
$upscope $end
$upscope $end
$upscope $end
$upscope $end
$scope module tb_mcu $end
$scope module mcuuq $end
$scope module cpu $end
$scope module rf $end
$var reg 32 u \mem[2] [31:0] $end
$upscope $end
$upscope $end
$upscope $end
$upscope $end
$scope module tb_mcu $end
$scope module mcuuq $end
$scope module cpu $end
$scope module rf $end
$var reg 32 v \mem[3] [31:0] $end
$upscope $end
$upscope $end
$upscope $end
$upscope $end
$scope module tb_mcu $end
$scope module mcuuq $end
$scope module cpu $end
$scope module rf $end
$var reg 32 w \mem[4] [31:0] $end
$upscope $end
$upscope $end
$upscope $end
$upscope $end
$scope module tb_mcu $end
$scope module mcuuq $end
$scope module cpu $end
$scope module rf $end
$var reg 32 x \mem[5] [31:0] $end
$upscope $end
$upscope $end
$upscope $end
$upscope $end
$scope module tb_mcu $end
$scope module mcuuq $end
$scope module cpu $end
$scope module rf $end
$var reg 32 y \mem[6] [31:0] $end
$upscope $end
$upscope $end
$upscope $end
$upscope $end
$scope module tb_mcu $end
$scope module mcuuq $end
$scope module cpu $end
$scope module rf $end
$var reg 32 z \mem[7] [31:0] $end
$upscope $end
$upscope $end
$upscope $end
$upscope $end
$scope module tb_mcu $end
$scope module mcuuq $end
$scope module cpu $end
$scope module rf $end
$var reg 32 { \mem[8] [31:0] $end
$upscope $end
$upscope $end
$upscope $end
$upscope $end
$scope module tb_mcu $end
$scope module mcuuq $end
$scope module cpu $end
$scope module rf $end
$var reg 32 | \mem[9] [31:0] $end
$upscope $end
$upscope $end
$upscope $end
$upscope $end
$scope module tb_mcu $end
$scope module mcuuq $end
$scope module cpu $end
$scope module rf $end
$var reg 32 } \mem[10] [31:0] $end
$upscope $end
$upscope $end
$upscope $end
$upscope $end
$scope module tb_mcu $end
$scope module mcuuq $end
$scope module cpu $end
$scope module rf $end
$var reg 32 ~ \mem[11] [31:0] $end
$upscope $end
$upscope $end
$upscope $end
$upscope $end
$scope module tb_mcu $end
$scope module mcuuq $end
$scope module cpu $end
$scope module rf $end
$var reg 32 !" \mem[12] [31:0] $end
$upscope $end
$upscope $end
$upscope $end
$upscope $end
$scope module tb_mcu $end
$scope module mcuuq $end
$scope module cpu $end
$scope module rf $end
$var reg 32 "" \mem[13] [31:0] $end
$upscope $end
$upscope $end
$upscope $end
$upscope $end
$scope module tb_mcu $end
$scope module mcuuq $end
$scope module cpu $end
$scope module rf $end
$var reg 32 #" \mem[14] [31:0] $end
$upscope $end
$upscope $end
$upscope $end
$upscope $end
$scope module tb_mcu $end
$scope module mcuuq $end
$scope module cpu $end
$scope module rf $end
$var reg 32 $" \mem[15] [31:0] $end
$upscope $end
$upscope $end
$upscope $end
$upscope $end
$scope module tb_mcu $end
$scope module mcuuq $end
$scope module cpu $end
$scope module rf $end
$var reg 32 %" \mem[16] [31:0] $end
$upscope $end
$upscope $end
$upscope $end
$upscope $end
$scope module tb_mcu $end
$scope module mcuuq $end
$scope module cpu $end
$scope module rf $end
$var reg 32 &" \mem[17] [31:0] $end
$upscope $end
$upscope $end
$upscope $end
$upscope $end
$scope module tb_mcu $end
$scope module mcuuq $end
$scope module cpu $end
$scope module rf $end
$var reg 32 '" \mem[18] [31:0] $end
$upscope $end
$upscope $end
$upscope $end
$upscope $end
$scope module tb_mcu $end
$scope module mcuuq $end
$scope module cpu $end
$scope module rf $end
$var reg 32 (" \mem[19] [31:0] $end
$upscope $end
$upscope $end
$upscope $end
$upscope $end
$scope module tb_mcu $end
$scope module mcuuq $end
$scope module cpu $end
$scope module rf $end
$var reg 32 )" \mem[20] [31:0] $end
$upscope $end
$upscope $end
$upscope $end
$upscope $end
$scope module tb_mcu $end
$scope module mcuuq $end
$scope module cpu $end
$scope module rf $end
$var reg 32 *" \mem[21] [31:0] $end
$upscope $end
$upscope $end
$upscope $end
$upscope $end
$scope module tb_mcu $end
$scope module mcuuq $end
$scope module cpu $end
$scope module rf $end
$var reg 32 +" \mem[22] [31:0] $end
$upscope $end
$upscope $end
$upscope $end
$upscope $end
$scope module tb_mcu $end
$scope module mcuuq $end
$scope module cpu $end
$scope module rf $end
$var reg 32 ," \mem[23] [31:0] $end
$upscope $end
$upscope $end
$upscope $end
$upscope $end
$scope module tb_mcu $end
$scope module mcuuq $end
$scope module cpu $end
$scope module rf $end
$var reg 32 -" \mem[24] [31:0] $end
$upscope $end
$upscope $end
$upscope $end
$upscope $end
$scope module tb_mcu $end
$scope module mcuuq $end
$scope module cpu $end
$scope module rf $end
$var reg 32 ." \mem[25] [31:0] $end
$upscope $end
$upscope $end
$upscope $end
$upscope $end
$scope module tb_mcu $end
$scope module mcuuq $end
$scope module cpu $end
$scope module rf $end
$var reg 32 /" \mem[26] [31:0] $end
$upscope $end
$upscope $end
$upscope $end
$upscope $end
$scope module tb_mcu $end
$scope module mcuuq $end
$scope module cpu $end
$scope module rf $end
$var reg 32 0" \mem[27] [31:0] $end
$upscope $end
$upscope $end
$upscope $end
$upscope $end
$scope module tb_mcu $end
$scope module mcuuq $end
$scope module cpu $end
$scope module rf $end
$var reg 32 1" \mem[28] [31:0] $end
$upscope $end
$upscope $end
$upscope $end
$upscope $end
$scope module tb_mcu $end
$scope module mcuuq $end
$scope module cpu $end
$scope module rf $end
$var reg 32 2" \mem[29] [31:0] $end
$upscope $end
$upscope $end
$upscope $end
$upscope $end
$scope module tb_mcu $end
$scope module mcuuq $end
$scope module cpu $end
$scope module rf $end
$var reg 32 3" \mem[30] [31:0] $end
$upscope $end
$upscope $end
$upscope $end
$upscope $end
$scope module tb_mcu $end
$scope module mcuuq $end
$scope module cpu $end
$scope module rf $end
$var reg 32 4" \mem[31] [31:0] $end
$upscope $end
$upscope $end
$upscope $end
$upscope $end
$enddefinitions $end
$comment Show the parameter values. $end
$dumpall
$end
#0
$dumpvars
b0 4"
b0 3"
b0 2"
b0 1"
b0 0"
b0 /"
b0 ."
b0 -"
b0 ,"
b0 +"
b0 *"
b0 )"
b0 ("
b0 '"
b0 &"
b0 %"
b0 $"
b0 #"
b0 ""
b0 !"
b0 ~
b0 }
b0 |
b0 {
b0 z
b0 y
b0 x
b0 w
b0 v
b0 u
b0 t
b0 s
b100000 r
bx q
bx p
0o
bx n
bx m
bx l
bx k
b0 j
bx i
bx h
b0x g
b0x f
bx e
bx d
bx c
1b
0a
0`
bx _
bx ^
bx ]
bx \
bx [
b0 Z
bx0 Y
bx X
xW
xV
xU
xT
bx S
bx R
xQ
bx P
bx O
xN
xM
xL
xK
xJ
xI
bx0 H
bx G
bx F
bx E
bx D
bx C
bx B
bx A
bx000000000000 @
bx ?
x>
x=
x<
x;
x:
x9
x8
x7
x6
x5
x4
bx 3
bx 2
b0 1
bz 0
b0 /
x.
x-
bx ,
bx +
bx *
bx )
0(
0'
b0 &
bz %
b0 $
b100000 #
1"
0!
$end
#2000
0<
1-
0.
b0 g
b100 G
b0 h
b0 f
b0 X
b0 i
b0 [
b0 e
b0 \
b0 d
b0 Y
b0 H
b0 O
0=
b0 ]
b0 c
0:
0>
04
09
07
05
08
06
1V
0U
0T
1W
b0 B
b0 q
b0 A
b0 p
0;
b0 P
b0 @
b110110011 )
b110110011 ,
b110110011 3
0I
0L
0M
0K
0J
0N
b0 F
b0 E
b0 m
b0 S
b0 D
b0 k
b0 C
b0 l
b0 R
0Q
b0 ?
b0 n
b0 +
b0 ^
b0 *
b0 2
b0 _
1!
#4000
0!
#6000
1!
#8000
0!
#10000
1!
#12000
0!
#14000
1!
#16000
0!
#18000
1!
#20000
0!
#22000
1!
#24000
0!
#26000
1!
#28000
0!
#30000
1!
#32000
0!
#34000
1!
#36000
0!
#38000
1!
#40000
0!
#42000
1!
#44000
0!
#46000
1!
#48000
0!
#50000
1!
#52000
0!
#54000
1!
#56000
0!
#58000
1!
#60000
0!
#62000
1!
#64000
0!
#66000
1!
#68000
0!
#70000
1!
#72000
0!
#74000
1!
#76000
0!
#78000
1!
#80000
0!
#82000
1!
#84000
0!
#86000
1!
#88000
0!
#90000
1!
#92000
0!
#93000
0"
#94000
1>
b100000000010 X
b100000000010 Y
1=
1I
b110011 F
b11 E
b11 m
b110110011 ^
1!
#96000
1`
0b
0!
#98000
1!
#100000
1o
1a
0`
0!
#102000
b1010110011 )
b1010110011 ,
b1010110011 3
b1000 G
b1 +
b100000000110 X
b100 *
b100 2
b100 _
b0 v
1!
#104000
0o
0a
1b
0!
#106000
b100000001000 X
b100000000100 Y
b101 E
b101 m
b1010110011 ^
1!
#108000
1`
0b
0!
#110000
1!
#112000
1o
1a
0`
0!
#114000
b10100000000001100010011 )
b10100000000001100010011 ,
b10100000000001100010011 3
b1100 G
b10 +
b0 x
b100000001100 X
b1000 *
b1000 2
b1000 _
1!
#116000
0o
0a
1b
0!
#118000
b101 ?
b101 n
b1 g
b101 Z
b101 j
b101 h
b1 f
b1110 X
b101 \
b101 d
b101 O
b110 Y
b100000000100 H
0=
b101 P
b10100000000000000000000 @
0I
1L
b10011 F
b110 E
b110 m
b101 C
b101 l
b10100000000001100010011 ^
1!
#120000
1`
0b
0!
#122000
1!
#124000
1o
1a
0`
0!
#126000
b10100011000000110110011 )
b10100011000000110110011 ,
b10100011000000110110011 3
b10000 G
b11 +
b10010 X
b1100 *
b1100 2
b1100 _
b101 y
1!
#128000
0o
0a
1b
0!
#130000
b0 ?
b0 n
b0 g
b0 Z
b0 j
b0 h
b0 f
b100000001110 X
b0 \
b0 d
b100000000010 Y
b11000100000000100 H
1=
b10100011000000000000000 @
1I
0L
b110011 F
b11 E
b11 m
b11 D
b11 k
b10100011000000110110011 ^
1!
#132000
1`
0b
0!
#134000
1!
#136000
1o
1a
0`
0!
#138000
b100101000001010010011 )
b100101000001010010011 ,
b100101000001010010011 3
b10100 G
b100 +
b0 v
b100000010010 X
b10000 *
b10000 2
b10000 _
1!
#140000
0o
0a
1b
0!
#142000
b1 ?
b1 n
b1 g
b1 Z
b1 j
b1 h
b1 f
b100000010100 X
b1 \
b1 d
b1 O
b100000000100 Y
b101000100000000000 H
0=
b1 P
b100101000000000000000 @
0I
1L
b10011 F
b101 E
b101 m
b101 D
b101 k
b1 C
b1 l
b100101000001010010011 ^
1!
#144000
1`
0b
0!
#146000
1!
#148000
1o
1a
0`
0!
#150000
b10 ?
b10 n
b0 g
b10 Z
b10 j
b1 i
b0 f
b1 ]
b1 c
b11111110011000101100110011100011 )
b11111110011000101100110011100011 ,
b11111110011000101100110011100011 3
b11000 G
b101 +
1T
0W
b1 B
b1 q
b100000011000 X
b10100 *
b10100 2
b10100 _
b1 x
1!
#152000
0o
0a
1b
0!
#154000
b1100 G
1<
b110 ?
b110 n
b1 g
0>
b110 Z
b110 j
b101 h
b1 f
0-
1.
b1100 X
b101 \
b101 d
0V
1U
b101 A
b101 p
b11111111111111111111111111100110 O
b11111111111111111111111111111000 Y
b11111111111100101100011111100110 H
17
b11111111111111111111111111100110 P
b11111110011000101100000000000000 @
0L
1M
b1100011 F
b11001 E
b11001 m
b100 S
b110 C
b110 l
b1111111 R
1Q
b11111110011000101100110011100011 ^
1!
#156000
1`
0b
0!
#158000
1!
#160000
1a
0`
0!
#162000
b10100011000000110110011 )
b10100011000000110110011 ,
b10100011000000110110011 3
b100 G
b11 +
b100 X
b1100 *
b1100 2
b1100 _
1!
#164000
0a
1b
0!
#166000
0<
b0 i
b1 ?
b1 n
b1 g
1>
b0 ]
b0 c
b1 Z
b1 j
b1 h
b1 f
b10000 G
b1 \
b1 d
b100000001110 X
b0 B
b0 q
0V
1U
1T
0W
b1 A
b1 p
b101 O
b100000000010 Y
b11000100000000100 H
1=
07
b101 P
b10100011000000000000000 @
1I
0M
b110011 F
b11 E
b11 m
b0 S
b11 D
b11 k
b101 C
b101 l
b0 R
0Q
b10100011000000110110011 ^
1!
#168000
1`
0b
0!
#170000
1!
#172000
1o
1a
0`
0!
#174000
b10 ?
b10 n
b0 g
b10 Z
b10 j
b1 i
b0 f
b1 ]
b1 c
b100101000001010010011 )
b100101000001010010011 ,
b100101000001010010011 3
1-
0.
b10100 G
b100 +
1V
0U
0T
1W
b1 B
b1 q
b100000010010 X
b10000 *
b10000 2
b10000 _
b1 v
1!
#176000
0o
0a
1b
0!
#178000
b100000010100 X
1T
0W
b0 A
b0 p
b1 O
b100000000100 Y
b101000100000000000 H
0=
b1 P
b100101000000000000000 @
0I
1L
b10011 F
b101 E
b101 m
b101 D
b101 k
b1 C
b1 l
b100101000001010010011 ^
1!
#180000
1`
0b
0!
#182000
1!
#184000
1o
1a
0`
0!
#186000
b11 ?
b11 n
b11 Z
b11 j
b10 i
b10 ]
b10 c
b11111110011000101100110011100011 )
b11111110011000101100110011100011 ,
b11111110011000101100110011100011 3
b10 B
b10 q
b11000 G
b101 +
b10 x
b100000011000 X
b10100 *
b10100 2
b10100 _
1!
#188000
0o
0a
1b
0!
#190000
b1100 G
1<
b111 ?
b111 n
b1 g
0>
b111 Z
b111 j
b101 h
b1 f
0-
1.
b1100 X
b101 \
b101 d
0V
1U
b101 A
b101 p
b11111111111111111111111111100110 O
b11111111111111111111111111111000 Y
b11111111111100101100011111100110 H
17
b11111111111111111111111111100110 P
b11111110011000101100000000000000 @
0L
1M
b1100011 F
b11001 E
b11001 m
b100 S
b110 C
b110 l
b1111111 R
1Q
b11111110011000101100110011100011 ^
1!
#192000
1`
0b
0!
#194000
1!
#196000
1a
0`
0!
#198000
b10100011000000110110011 )
b10100011000000110110011 ,
b10100011000000110110011 3
b100 G
b11 +
b100 X
b1100 *
b1100 2
b1100 _
1!
#200000
0a
1b
0!
#202000
0<
b1 i
b11 ?
b11 n
b1 g
1>
b1 ]
b1 c
b11 Z
b11 j
b10 h
b1 f
b10000 G
b10 \
b10 d
b100000001110 X
b1 B
b1 q
0V
1U
1T
0W
b10 A
b10 p
b101 O
b100000000010 Y
b11000100000000100 H
1=
07
b101 P
b10100011000000000000000 @
1I
0M
b110011 F
b11 E
b11 m
b0 S
b11 D
b11 k
b101 C
b101 l
b0 R
0Q
b10100011000000110110011 ^
1!
#204000
1`
0b
0!
#206000
1!
#208000
1o
1a
0`
0!
#210000
b101 ?
b101 n
b0 g
b101 Z
b101 j
b11 i
b0 f
b11 ]
b11 c
1-
0.
b100101000001010010011 )
b100101000001010010011 ,
b100101000001010010011 3
1V
0U
b11 B
b11 q
b10100 G
b100 +
b11 v
b100000010010 X
b10000 *
b10000 2
b10000 _
1!
#212000
0o
0a
1b
0!
#214000
b10 i
b11 ?
b11 n
b10 ]
b10 c
b11 Z
b11 j
b1 h
b100000010100 X
b1 \
b1 d
b10 B
b10 q
b0 A
b0 p
b1 O
b100000000100 Y
b101000100000000000 H
0=
b1 P
b100101000000000000000 @
0I
1L
b10011 F
b101 E
b101 m
b101 D
b101 k
b1 C
b1 l
b100101000001010010011 ^
1!
#216000
1`
0b
0!
#218000
1!
#220000
1o
1a
0`
0!
#222000
b100 ?
b100 n
b100 Z
b100 j
b11 i
b11 ]
b11 c
b11111110011000101100110011100011 )
b11111110011000101100110011100011 ,
b11111110011000101100110011100011 3
b11000 G
b101 +
b11 B
b11 q
b100000011000 X
b10100 *
b10100 2
b10100 _
b11 x
1!
#224000
0o
0a
1b
0!
#226000
b1100 G
1<
b1000 ?
b1000 n
b1 g
0>
b1000 Z
b1000 j
b101 h
b1 f
0-
1.
b1100 X
b101 \
b101 d
0V
1U
b101 A
b101 p
b11111111111111111111111111100110 O
b11111111111111111111111111111000 Y
b11111111111100101100011111100110 H
17
b11111111111111111111111111100110 P
b11111110011000101100000000000000 @
0L
1M
b1100011 F
b11001 E
b11001 m
b100 S
b110 C
b110 l
b1111111 R
1Q
b11111110011000101100110011100011 ^
1!
#228000
1`
0b
0!
#230000
1!
#232000
1a
0`
0!
#234000
b10100011000000110110011 )
b10100011000000110110011 ,
b10100011000000110110011 3
b100 G
b11 +
b100 X
b1100 *
b1100 2
b1100 _
1!
#236000
0a
1b
0!
#238000
0<
b110 ?
b110 n
b0 g
1>
b110 Z
b110 j
b11 h
b0 f
b10000 G
1-
0.
b11 \
b11 d
b100000001110 X
1V
0U
0T
1W
b11 A
b11 p
b101 O
b100000000010 Y
b11000100000000100 H
1=
07
b101 P
b10100011000000000000000 @
1I
0M
b110011 F
b11 E
b11 m
b0 S
b11 D
b11 k
b101 C
b101 l
b0 R
0Q
b10100011000000110110011 ^
1!
#240000
1`
0b
0!
#242000
1!
#244000
1o
1a
0`
0!
