alu.v
module alu (
    input [31:0] A,
    input [31:0] B,
    input [2:0] op,
    output [31:0] ALU_out
);

    assign ALU_out = 
        (op == 3'b000) ? A + B :  // Suma (add)
        (op == 3'b001) ? A - B :  // Resta (sub)
        (op == 3'b010) ? A & B :  // AND (and)
        (op == 3'b011) ? A | B :  // OR (or)
        (op == 3'b100) ? A ^ B :  // XOR (xor)
                         32'd0;

endmodule

registerfile.v
module registerfile(
    input clk,
    input wr_en,
    input [4:0] wr_index,
    input [31:0] wr_data,
    input [4:0] rd_index1,
    input [4:0] rd_index2,
    output [31:0] rd_data1,
    output [31:0] rd_data2
);

    // Memoria de 32 posiciones de 32 bits
    reg [31:0] mem [0:31];

    // Lógica de lectura combinacional (dual-port)
    // El registro x0 (dirección 0) siempre se lee cero
    assign rd_data1 = (rd_index1 == 5'b00000) ? 32'd0 : mem[rd_index1];
    assign rd_data2 = (rd_index2 == 5'b00000) ? 32'd0 : mem[rd_index2];

    // Lógica de escritura secuencial / sincrónica
    always @(posedge clk) begin
        // Si la escritura está habilitada y no se intenta escribir en x0
        if (wr_en && (wr_index != 5'b00000)) begin
            mem[wr_index] <= wr_data;
        end
    end

endmodule

riscv.v
module riscv (
    input clk,          // Reloj del procesador
    input rst,          // Reset del procesador
    input [31:0] instr  // Instrucción de entrada
);

    reg [31:0] IR; // Registro de instrucción
    always @(posedge clk) begin
        IR <= instr;
    end

    // Señales del registro de instrucción (IR)
    wire [6:0] funct7;
    wire [4:0] rs2;
    wire [4:0] rs1;
    wire [2:0] funct3;
    wire [4:0] rd;
    wire [6:0] opcode;

    // Extracción de los campos del registro de instrucción (Formatos de 32 bits)
    assign funct7 = IR[31:25];
    assign rs2    = IR[24:20];
    assign rs1    = IR[19:15];
    assign funct3 = IR[14:12];
    assign rd     = IR[11:7];
    assign opcode = IR[6:0];

    // Salidas del register file
    wire [31:0] src1_value;
    wire [31:0] src2_value;

    // Operandos de entrada a la ALU
    wire [31:0] alu_a;
    wire [31:0] alu_b;

    // Salida de la ALU
    wire [31:0] alu_out;

    // Señales de control de la Unidad de Control (CU)
    wire wr_en;
    wire [10:0] dec_bits;
    wire is_add;
    wire is_sub;
    wire is_and;
    wire is_or;
    wire is_xor;

    // Cableado entre el RF y la ALU
    assign alu_a = src1_value;
    assign alu_b = src2_value;

    // Cableado de la Control Unit (CU)
    assign dec_bits = {funct7[5], funct3, opcode};

    // Identificación de instrucciones según la especificación RISC-V (pg. 44)
    assign is_add = (dec_bits == 11'b0_000_0110011);
    assign is_sub = (dec_bits == 11'b1_000_0110011);
    assign is_xor = (dec_bits == 11'b0_100_0110011);
    assign is_or  = (dec_bits == 11'b0_110_0110011);
    assign is_and = (dec_bits == 11'b0_111_0110011);

    // Habilitador de escritura (wr_en)
    assign wr_en = is_add | is_sub | is_xor | is_or | is_and;

    // Código de operación enviado a la ALU
    wire [2:0] alu_op;
    assign alu_op = is_add ? 3'b000 :
                    is_sub ? 3'b001 :
                    is_and ? 3'b010 :
                    is_or  ? 3'b011 :
                    is_xor ? 3'b100 : 3'b000;

    // Instanciación del Register File (RF)
    registerfile rv_rf (
        .clk(clk),
        .wr_en(wr_en),
        .wr_index(rd),
        .wr_data(alu_out),
        .rd_index1(rs1),
        .rd_data1(src1_value),
        .rd_index2(rs2),
        .rd_data2(src2_value)
    );

    // Instanciación de la ALU
    alu rv_alu (
        .A(alu_a),
        .B(alu_b),
        .ALU_out(alu_out),
        .op(alu_op)
    );

endmodule

riscv_tb.v
`timescale 1ns/1ps

module tb_riscv;

    // Señales de prueba
    reg [31:0] instr;
    reg clk;
    reg rst;

    // Instancia del DUT
    riscv uut (
        .clk(clk),
        .rst(rst),
        .instr(instr)
    );

    integer i;
    initial begin
        $dumpfile("tb_riscv.vcd");
        $dumpvars(0, tb_riscv);

        for(i = 0; i < 32; i = i + 1) $dumpvars(0, uut.rv_rf.mem[i]);
        for(i = 0; i < 32; i = i + 1) uut.rv_rf.mem[i] = i;

        $monitor($time, " clk=%b ins=%h x4=%h x5=%h x6=%h x7=%h x8=%h", 
                 clk, instr,
                 uut.rv_rf.mem[4], uut.rv_rf.mem[5], uut.rv_rf.mem[6], uut.rv_rf.mem[7], uut.rv_rf.mem[8]);

        clk = 0; 
        rst = 1;
        #10; 
        rst = 0;

        // 1. ADD: x4 = x3 + x2 = 3 + 2 = 5
        $display("--- add x4, x3, x2 ---");
        instr = 32'b0000000_00010_00011_000_00100_0110011; 
        #16;

        // 2. SUB: x5 = x3 - x2 = 3 - 2 = 1
        $display("--- sub x5, x3, x2 ---");
        instr = 32'b0100000_00010_00011_000_00101_0110011; 
        #16;

        // 3. AND: x6 = x10 & x12 = 10 & 12 = 8
        $display("--- and x6, x10, x12 ---");
        instr = 32'b0000000_01100_01010_111_00110_0110011; 
        #16;

        // 4. OR: x7 = x10 | x12 = 10 | 12 = 14 (0xE)
        $display("--- or x7, x10, x12 ---");
        instr = 32'b0000000_01100_01010_110_00111_0110011; 
        #16;

        // 5. XOR: x8 = x10 ^ x12 = 10 ^ 12 = 6
        $display("--- xor x8, x10, x12 ---");
        instr = 32'b0000000_01100_01010_100_01000_0110011; 
        #16;

        $finish;
    end

    // Generador de reloj
    always #2 clk = ~clk;

endmodule

tb_riscv.vcd
$date
	Wed Sep  9 10:00:56 2026
$end
$version
	Icarus Verilog
$end
$timescale
	1ps
$end
$scope module tb_riscv $end
$var reg 1 ! clk $end
$var reg 32 " instr [31:0] $end
$var reg 1 # rst $end
$var integer 32 $ i [31:0] $end
$scope module uut $end
$var wire 32 % alu_a [31:0] $end
$var wire 32 & alu_b [31:0] $end
$var wire 1 ! clk $end
$var wire 32 ' instr [31:0] $end
$var wire 1 # rst $end
$var wire 1 ( wr_en $end
$var wire 32 ) src2_value [31:0] $end
$var wire 32 * src1_value [31:0] $end
$var wire 5 + rs2 [4:0] $end
$var wire 5 , rs1 [4:0] $end
$var wire 5 - rd [4:0] $end
$var wire 7 . opcode [6:0] $end
$var wire 1 / is_xor $end
$var wire 1 0 is_sub $end
$var wire 1 1 is_or $end
$var wire 1 2 is_and $end
$var wire 1 3 is_add $end
$var wire 7 4 funct7 [6:0] $end
$var wire 3 5 funct3 [2:0] $end
$var wire 11 6 dec_bits [10:0] $end
$var wire 32 7 alu_out [31:0] $end
$var wire 3 8 alu_op [2:0] $end
$var reg 32 9 IR [31:0] $end
$scope module rv_alu $end
$var wire 32 : A [31:0] $end
$var wire 32 ; B [31:0] $end
$var wire 3 < op [2:0] $end
$var wire 32 = ALU_out [31:0] $end
$upscope $end
$scope module rv_rf $end
$var wire 1 ! clk $end
$var wire 5 > rd_index1 [4:0] $end
$var wire 5 ? rd_index2 [4:0] $end
$var wire 32 @ wr_data [31:0] $end
$var wire 1 ( wr_en $end
$var wire 5 A wr_index [4:0] $end
$var wire 32 B rd_data2 [31:0] $end
$var wire 32 C rd_data1 [31:0] $end
$upscope $end
$upscope $end
$upscope $end
$scope module tb_riscv $end
$scope module uut $end
$scope module rv_rf $end
$var reg 32 D \mem[0] [31:0] $end
$upscope $end
$upscope $end
$upscope $end
$scope module tb_riscv $end
$scope module uut $end
$scope module rv_rf $end
$var reg 32 E \mem[1] [31:0] $end
$upscope $end
$upscope $end
$upscope $end
$scope module tb_riscv $end
$scope module uut $end
$scope module rv_rf $end
$var reg 32 F \mem[2] [31:0] $end
$upscope $end
$upscope $end
$upscope $end
$scope module tb_riscv $end
$scope module uut $end
$scope module rv_rf $end
$var reg 32 G \mem[3] [31:0] $end
$upscope $end
$upscope $end
$upscope $end
$scope module tb_riscv $end
$scope module uut $end
$scope module rv_rf $end
$var reg 32 H \mem[4] [31:0] $end
$upscope $end
$upscope $end
$upscope $end
$scope module tb_riscv $end
$scope module uut $end
$scope module rv_rf $end
$var reg 32 I \mem[5] [31:0] $end
$upscope $end
$upscope $end
$upscope $end
$scope module tb_riscv $end
$scope module uut $end
$scope module rv_rf $end
$var reg 32 J \mem[6] [31:0] $end
$upscope $end
$upscope $end
$upscope $end
$scope module tb_riscv $end
$scope module uut $end
$scope module rv_rf $end
$var reg 32 K \mem[7] [31:0] $end
$upscope $end
$upscope $end
$upscope $end
$scope module tb_riscv $end
$scope module uut $end
$scope module rv_rf $end
$var reg 32 L \mem[8] [31:0] $end
$upscope $end
$upscope $end
$upscope $end
$scope module tb_riscv $end
$scope module uut $end
$scope module rv_rf $end
$var reg 32 M \mem[9] [31:0] $end
$upscope $end
$upscope $end
$upscope $end
$scope module tb_riscv $end
$scope module uut $end
$scope module rv_rf $end
$var reg 32 N \mem[10] [31:0] $end
$upscope $end
$upscope $end
$upscope $end
$scope module tb_riscv $end
$scope module uut $end
$scope module rv_rf $end
$var reg 32 O \mem[11] [31:0] $end
$upscope $end
$upscope $end
$upscope $end
$scope module tb_riscv $end
$scope module uut $end
$scope module rv_rf $end
$var reg 32 P \mem[12] [31:0] $end
$upscope $end
$upscope $end
$upscope $end
$scope module tb_riscv $end
$scope module uut $end
$scope module rv_rf $end
$var reg 32 Q \mem[13] [31:0] $end
$upscope $end
$upscope $end
$upscope $end
$scope module tb_riscv $end
$scope module uut $end
$scope module rv_rf $end
$var reg 32 R \mem[14] [31:0] $end
$upscope $end
$upscope $end
$upscope $end
$scope module tb_riscv $end
$scope module uut $end
$scope module rv_rf $end
$var reg 32 S \mem[15] [31:0] $end
$upscope $end
$upscope $end
$upscope $end
$scope module tb_riscv $end
$scope module uut $end
$scope module rv_rf $end
$var reg 32 T \mem[16] [31:0] $end
$upscope $end
$upscope $end
$upscope $end
$scope module tb_riscv $end
$scope module uut $end
$scope module rv_rf $end
$var reg 32 U \mem[17] [31:0] $end
$upscope $end
$upscope $end
$upscope $end
$scope module tb_riscv $end
$scope module uut $end
$scope module rv_rf $end
$var reg 32 V \mem[18] [31:0] $end
$upscope $end
$upscope $end
$upscope $end
$scope module tb_riscv $end
$scope module uut $end
$scope module rv_rf $end
$var reg 32 W \mem[19] [31:0] $end
$upscope $end
$upscope $end
$upscope $end
$scope module tb_riscv $end
$scope module uut $end
$scope module rv_rf $end
$var reg 32 X \mem[20] [31:0] $end
$upscope $end
$upscope $end
$upscope $end
$scope module tb_riscv $end
$scope module uut $end
$scope module rv_rf $end
$var reg 32 Y \mem[21] [31:0] $end
$upscope $end
$upscope $end
$upscope $end
$scope module tb_riscv $end
$scope module uut $end
$scope module rv_rf $end
$var reg 32 Z \mem[22] [31:0] $end
$upscope $end
$upscope $end
$upscope $end
$scope module tb_riscv $end
$scope module uut $end
$scope module rv_rf $end
$var reg 32 [ \mem[23] [31:0] $end
$upscope $end
$upscope $end
$upscope $end
$scope module tb_riscv $end
$scope module uut $end
$scope module rv_rf $end
$var reg 32 \ \mem[24] [31:0] $end
$upscope $end
$upscope $end
$upscope $end
$scope module tb_riscv $end
$scope module uut $end
$scope module rv_rf $end
$var reg 32 ] \mem[25] [31:0] $end
$upscope $end
$upscope $end
$upscope $end
$scope module tb_riscv $end
$scope module uut $end
$scope module rv_rf $end
$var reg 32 ^ \mem[26] [31:0] $end
$upscope $end
$upscope $end
$upscope $end
$scope module tb_riscv $end
$scope module uut $end
$scope module rv_rf $end
$var reg 32 _ \mem[27] [31:0] $end
$upscope $end
$upscope $end
$upscope $end
$scope module tb_riscv $end
$scope module uut $end
$scope module rv_rf $end
$var reg 32 ` \mem[28] [31:0] $end
$upscope $end
$upscope $end
$upscope $end
$scope module tb_riscv $end
$scope module uut $end
$scope module rv_rf $end
$var reg 32 a \mem[29] [31:0] $end
$upscope $end
$upscope $end
$upscope $end
$scope module tb_riscv $end
$scope module uut $end
$scope module rv_rf $end
$var reg 32 b \mem[30] [31:0] $end
$upscope $end
$upscope $end
$upscope $end
$scope module tb_riscv $end
$scope module uut $end
$scope module rv_rf $end
$var reg 32 c \mem[31] [31:0] $end
$upscope $end
$upscope $end
$upscope $end
$enddefinitions $end
$comment Show the parameter values. $end
$dumpall
$end
#0
$dumpvars
b11111 c
b11110 b
b11101 a
b11100 `
b11011 _
b11010 ^
b11001 ]
b11000 \
b10111 [
b10110 Z
b10101 Y
b10100 X
b10011 W
b10010 V
b10001 U
b10000 T
b1111 S
b1110 R
b1101 Q
b1100 P
b1011 O
b1010 N
b1001 M
b1000 L
b111 K
b110 J
b101 I
b100 H
b11 G
b10 F
b1 E
b0 D
bx C
bx B
bx A
bx @
bx ?
bx >
bx =
bx <
bx ;
bx :
bx 9
bx 8
bx 7
bx 6
bx 5
bx 4
x3
x2
x1
x0
x/
bx .
bx -
bx ,
bx +
bx *
bx )
x(
bx '
bx &
bx %
b100000 $
1#
bx "
0!
$end
#2000
1!
#4000
0!
#6000
1!
#8000
0!
#10000
1(
b101 7
b101 =
b101 @
b0 8
b0 <
13
00
b10 &
b10 ;
b10 )
b10 B
b11 %
b11 :
b11 *
b11 C
0/
01
02
b110011 6
b0 4
b10 +
b10 ?
b11 ,
b11 >
b0 5
b100 -
b100 A
b110011 .
b1000011000001000110011 9
1!
b1000011000001000110011 "
b1000011000001000110011 '
0#
#12000
0!
#14000
b101 H
1!
#16000
0!
#18000
b101 H
1!
#20000
0!
#22000
b101 H
1!
#24000
0!
#26000
b1 7
b1 =
b1 @
b1 8
b1 <
03
10
b10000110011 6
b100000 4
b101 -
b101 A
b101 H
b1000000001000011000001010110011 9
1!
b1000000001000011000001010110011 "
b1000000001000011000001010110011 '
#28000
0!
#30000
b1 I
1!
#32000
0!
#34000
b1 I
1!
#36000
0!
#38000
b1 I
1!
#40000
0!
#42000
b1000 7
b1000 =
b1000 @
b10 8
b10 <
12
b1100 &
b1100 ;
b1100 )
b1100 B
b1010 %
b1010 :
b1010 *
b1010 C
00
b1110110011 6
b0 4
b1100 +
b1100 ?
b1010 ,
b1010 >
b111 5
b110 -
b110 A
b1 I
b110001010111001100110011 9
1!
b110001010111001100110011 "
b110001010111001100110011 '
#44000
0!
#46000
b1000 J
1!
#48000
0!
#50000
b1000 J
1!
#52000
0!
#54000
b1000 J
1!
#56000
0!
#58000
b1110 7
b1110 =
b1110 @
b11 8
b11 <
1(
11
02
b1100110011 6
b110 5
b111 -
b111 A
b1000 J
b110001010110001110110011 9
1!
b110001010110001110110011 "
b110001010110001110110011 '
#60000
0!
#62000
b1110 K
1!
#64000
0!
#66000
b1110 K
1!
#68000
0!
#70000
b1110 K
1!
#72000
0!
#74000
b110 7
b110 =
b110 @
b100 8
b100 <
1(
1/
01
b1000110011 6
b100 5
b1000 -
b1000 A
b1110 K
b110001010100010000110011 9
1!
b110001010100010000110011 "
b110001010100010000110011 '
#76000
0!
#78000
b110 L
1!
#80000
0!
#82000
b110 L
1!
#84000
0!
#86000
b110 L
1!
#88000
0!
#90000
b110 L
1!
